Workbook

Sheet Summary
A1: ERJ Remote Job Search Sheet — 31 Oct 2026
A2: Roles posted or first appearing from 29 Oct (including those that showed up after the 29 Oct sheet was made) to 31 Oct · fully remote · open to Nigeria · no repeated links
A4: Tab | B4: Open — Nigeria eligible | C4: Check before applying | D4: Total
A5: Customer Support | B5: =COUNTIF('Customer Support'!$E$5:$E$6,"Open*") -> 1 | C5: =COUNTIF('Customer Support'!$E$5:$E$6,"Check*") -> 0 | D5: =B5+C5 -> 1
A6: VA & Admin | B6: =COUNTIF('VA & Admin'!$E$5:$E$12,"Open*") -> 6 | C6: =COUNTIF('VA & Admin'!$E$5:$E$12,"Check*") -> 0 | D6: =B6+C6 -> 6
A7: HR & Legal | B7: =COUNTIF('HR & Legal'!$E$5:$E$8,"Open*") -> 2 | C7: =COUNTIF('HR & Legal'!$E$5:$E$8,"Check*") -> 0 | D7: =B7+C7 -> 2
A8: Sales | B8: =COUNTIF(Sales!$E$5:$E$6,"Open*") -> 1 | C8: =COUNTIF(Sales!$E$5:$E$6,"Check*") -> 0 | D8: =B8+C8 -> 1
A9: Marketing & Creative | B9: =COUNTIF('Marketing & Creative'!$E$5:$E$12,"Open*") -> 5 | C9: =COUNTIF('Marketing & Creative'!$E$5:$E$12,"Check*") -> 0 | D9: =B9+C9 -> 5
A10: Tech & Operations | B10: =COUNTIF('Tech & Operations'!$E$5:$E$16,"Open*") -> 9 | C10: =COUNTIF('Tech & Operations'!$E$5:$E$16,"Check*") -> 0 | D10: =B10+C10 -> 9
A11: micro1 Referral | B11: =COUNTA('micro1 Referral'!$G$5:$G$7) -> 2 | C11: 0 | D11: =B11+C11 -> 2
A12: Total | B12: =SUM(B5:B11) -> 26 | C12: =SUM(C5:C11) -> 0 | D12: =SUM(D5:D11) -> 26
A14: Notes
A15: • Rule used: the posting names Nigeria, Africa, or worldwide/anywhere. EMEA-only, plain "Remote" and roles with office days were left out.
A16: • Every link here is new: none appears on the 29 Oct sheet or any earlier ERJ sheet.
A17: • Wider web search added OpenFn (Africa-wide) and a new 10Alytics role. Openhill Global: nothing new.
A18: • micro1 posted mostly language roles this week; only English-only, worldwide roles are listed.
A19: • Left out: micro1 foreign-language and voice roles, British English Voice Expert (native UK accent), US-only Inpatient Coder, Defense Analyst and U.S. Government engineer; Veta Virtual Accountant (LATAM/Europe only); Netlify talent pool (not a job); 20four7VA bilingual receptionist; Jobgether German localization; South Africa-only VA, paralegal and recruiter roles; Moniepoint People Helpdesk roles (EU board only).

Sheet Customer Support
A1: Customer Support — new remote roles open to Nigeria (31 Oct 2026)
A2: Posted or first appeared 29–31 Oct 2026 · fully remote · open to people in Nigeria · no link from any earlier ERJ sheet.
A4: # | B4: Who can apply | C4: Role | D4: Company | E4: Status | F4: Level | G4: Pay (as listed) | H4: Key requirements | I4: Source | J4: Posted | K4: Apply link | L4: Note
A5: ▸ Worldwide / global
A6: 1 | B6: Worldwide / Serbia / Spain / Poland / Georgia | C6: Product Owner (Customer Experience) | D6: Social Discovery Group | E6: Open — Nigeria eligible | F6: 3+ years | G6: $5000 | H6: Own the customer journey end-to-end, from registration to quality conversations, identifying friction points; Dig into data yourself: explore analytics with AI tools (e.g., querying BigQuery via MCP), validate insights, and turn them into strong | I6: Breezy | J6: 30 Oct | K6: Apply ↗

Sheet VA & Admin
A1: VA & Admin — new remote roles open to Nigeria (31 Oct 2026)
A2: Posted or first appeared 29–31 Oct 2026 · fully remote · open to people in Nigeria · no link from any earlier ERJ sheet.
A4: # | B4: Who can apply | C4: Role | D4: Company | E4: Status | F4: Level | G4: Pay (as listed) | H4: Key requirements | I4: Source | J4: Posted | K4: Apply link | L4: Note
A5: ▸ Worldwide / global
A6: 1 | B6: Worldwide | C6: Executive & Business Operations Virtual Assistant | D6: 20four7VA | E6: Open — Nigeria eligible | F6: Not stated | G6: Undisclosed | H6: Administrative, executive assistant, or business operations experience required; Excellent written English and professional email communication required | I6: Breezy | J6: 29 Oct | K6: Apply ↗
A7: 2 | B7: Worldwide | C7: Logistics & Inventory Management Virtual Assistant | D7: 20four7VA | E7: Open — Nigeria eligible | F7: Not stated | G7: Undisclosed | H7: Experience in inventory management, logistics coordination, supply chain support, or e-commerce operations; Familiarity with Shopify strongly preferred | I7: Breezy | J7: 29 Oct | K7: Apply ↗
A8: 3 | B8: Worldwide / Philippines | C8: Publishing Operations Virtual Assistant | D8: 20four7VA | E8: Open — Nigeria eligible | F8: Not stated | G8: Undisclosed | H8: Hands-on Amazon KDP publishing experience strongly preferred; Excellent written English and strong proofreading skills required | I8: Breezy | J8: 29 Oct | K8: Apply ↗
A9: 4 | B9: Worldwide | C9: Social Media & Grant Application Support Virtual Assistant | D9: 20four7VA | E9: Open — Nigeria eligible | F9: Not stated | G9: Undisclosed | H9: Social media content creation and publishing experience required; Strong written English and caption-writing skills required | I9: Breezy | J9: 29 Oct | K9: Apply ↗
A10: 5 | B10: Worldwide | C10: Social Media Community Engagement & Outreach Virtual Assistant | D10: 20four7VA | E10: Open — Nigeria eligible | F10: Not stated | G10: Undisclosed | H10: Experience in social media management, community engagement, or online outreach; Strong written English and the ability to write natural, professional, and personalized comments | I10: Breezy | J10: 30 Oct | K10: Apply ↗
A11: ▸ Nigeria-based remote
A12: 6 | B12: Remote (Nigerian company) | C12: Quality Assurance & Intern Support Officer | D12: 10Alytics | E12: Open — Nigeria eligible | F12: See posting | G12: Not listed | H12: Session coordination, intern engagement and quality checks; 2–3 yrs | I12: Career page | J12: 30 Oct | K12: Apply ↗

Sheet HR & Legal
A1: HR & Legal — new remote roles open to Nigeria (31 Oct 2026)
A2: Posted or first appeared 29–31 Oct 2026 · fully remote · open to people in Nigeria · no link from any earlier ERJ sheet.
A4: # | B4: Who can apply | C4: Role | D4: Company | E4: Status | F4: Level | G4: Pay (as listed) | H4: Key requirements | I4: Source | J4: Posted | K4: Apply link | L4: Note
A5: ▸ Worldwide / global
A6: 1 | B6: Remote / ALX Africa | C6: Talent Engagement Lead | D6: ALX Africa | E6: Open — Nigeria eligible | F6: 8–10 years | G6: Undisclosed | H6: 8 to 10 years of relevant experience in learning and development, talent development, organisational development, employee experience; Experience leading a similar function or multidisciplinary team | I6: Greenhouse | J6: 30 Oct | K6: Apply ↗
A7: ▸ Nigeria-based remote
A8: 2 | B8: Nigeria (Remote) / Nigeria (Remote) | C8: Head of Compliance & MLRO - Nigeria | D8: OKX | E8: Open — Nigeria eligible | F8: 8+ years | G8: Undisclosed | H8: Deep understanding of FATF Recommendations and their application to virtual asset service providers, including the Travel Rule; Strong knowledge of crypto-specific AML typologies | I8: Greenhouse | J8: 29 Oct | K8: Apply ↗

Sheet Sales
A1: Sales — new remote roles open to Nigeria (31 Oct 2026)
A2: Posted or first appeared 29–31 Oct 2026 · fully remote · open to people in Nigeria · no link from any earlier ERJ sheet.
A4: # | B4: Who can apply | C4: Role | D4: Company | E4: Status | F4: Level | G4: Pay (as listed) | H4: Key requirements | I4: Source | J4: Posted | K4: Apply link | L4: Note
A5: ▸ Worldwide / global
A6: 1 | B6: Anywhere in the World | C6: Sales Development Representative - Strategics | D6: Legion | E6: Open — Nigeria eligible | F6: 2+ years | G6: $70,000.00 - $80,000.00 | H6: 2 years of sales development prospecting experience for Saas company; Comfortable prospecting, cold calling, and overcoming objections | I6: We Work Remotely | J6: 29 Oct | K6: Apply ↗ | L6: Listed on We Work Remotely (no login needed)

Sheet Marketing & Creative
A1: Marketing & Creative — new remote roles open to Nigeria (31 Oct 2026)
A2: Posted or first appeared 29–31 Oct 2026 · fully remote · open to people in Nigeria · no link from any earlier ERJ sheet.
A4: # | B4: Who can apply | C4: Role | D4: Company | E4: Status | F4: Level | G4: Pay (as listed) | H4: Key requirements | I4: Source | J4: Posted | K4: Apply link | L4: Note
A5: ▸ Worldwide / global
A6: 1 | B6: Worldwide | C6: Project-Based Graphic Designer | D6: 20four7VA | E6: Open — Nigeria eligible | F6: Not stated | G6: Undisclosed | H6: Strong proficiency in Canva, including creating and editing professional design assets and reusable templates; Experience in graphic design, branding, and social media marketing materials | I6: Breezy | J6: 30 Oct | K6: Apply ↗
A7: 2 | B7: Anywhere in the World | C7: Marketing Manager, MENAT | D7: Roblox | E7: Open — Nigeria eligible | F7: 8+ years | G7: Undisclosed | H7: 8+ years of marketing experience with a deep, pan-regional focus across MENAT; Independent Drive | I7: We Work Remotely | J7: 29 Oct | K7: Apply ↗ | L7: Listed on We Work Remotely (no login needed)
A8: ▸ Region list incl. Nigeria
A9: 3 | B9: Egypt / Argentina / Nigeria | C9: Growth & Content Marketing Specialist (UGC) | D9: Scale Army | E9: Open — Nigeria eligible | F9: 3+ years | G9: $2.1K – $2.5K per month | H9: Strong ability to develop creative concepts, video scripts, and engaging hooks for short-form content; Ability to produce and edit 30-to-60-second UGC videos and software product demonstrations | I9: Ashby | J9: 29 Oct | K9: Apply ↗
A10: ▸ Nigeria-based remote
A11: 4 | B11: Remote — Lagos, Nigeria | C11: Creative Designer (Static and Motion) (PCS909) | D11: Hire Overseas | E11: Open — Nigeria eligible | F11: Not stated | G11: Undisclosed | H11: Proven creative design experience with a strong portfolio showing finished work across static formats including thumbnails; Genuine understanding of how design works in a video and motion context including visual hierarchy, pacing, and storytelling | I11: Workable | J11: 29 Oct | K11: Apply ↗
A12: 5 | B12: Nigeria | C12: Google Ads Media Buyer | D12: Jobgether partner | E12: Open — Nigeria eligible | F12: 1–2 years | G12: Undisclosed | H12: Manage Google Ads accounts end-to-end, taking ownership of campaign strategy, execution, optimization, budgets; Develop and implement performance-driven advertising strategies focused on generating sustainable profit | I12: Lever | J12: 30 Oct | K12: Apply ↗ | L12: Posted via Jobgether (partner company not named)

Sheet Tech & Operations
A1: Tech & Operations — new remote roles open to Nigeria (31 Oct 2026)
A2: Posted or first appeared 29–31 Oct 2026 · fully remote · open to people in Nigeria · no link from any earlier ERJ sheet.
A4: # | B4: Who can apply | C4: Role | D4: Company | E4: Status | F4: Level | G4: Pay (as listed) | H4: Key requirements | I4: Source | J4: Posted | K4: Apply link | L4: Note
A5: ▸ Worldwide / global
A6: 1 | B6: Remote - Global | C6: Software Engineer | D6: Centre for Effective Altruism | E6: Open — Nigeria eligible | F6: Not stated | G6: $134,900 - $166,725 | H6: This is a full-time, remote position | I6: Ashby | J6: 30 Oct | K6: Apply ↗
A7: 2 | B7: Anywhere in the World | C7: Senior Integration Engineer | D7: Legion | E7: Open — Nigeria eligible | F7: 7+ years | G7: $3,200 | H7: 7+ years of business/information/solution/technical architecture experience; Graduate of a university with a Bachelor's or Master's degree in a relevant STEM field, including Information Systems, Engineering | I7: We Work Remotely | J7: 29 Oct | K7: Apply ↗ | L7: Listed on We Work Remotely (no login needed)
A8: 3 | B8: Worldwide | C8: Deputy CDO | D8: Social Discovery Group | E8: Open — Nigeria eligible | F8: 6–10 years | G8: $5000 | H8: 6–10+ years in data, analytics, or ML domains, including 3–5+ years in leadership roles; Proven track record delivering cross-functional projects involving ML, data platforms, experimentation, and analytics | I8: Breezy | J8: 29 Oct | K8: Apply ↗
A9: 4 | B9: Poland / Georgia / Serbia / Worldwide | C9: Senior .NET Developer (Fintech) | D9: Social Discovery Group | E9: Open — Nigeria eligible | F9: 5+ years | G9: €2,800 per year | H9: 5+ years of commercial experience with C# and ASP.NET Core; Experience designing microservices | I9: Breezy | J9: 30 Oct | K9: Apply ↗
A10: 5 | B10: Europe, Middle East, Africa, Asia Pacific | C10: Vice President, International | D10: Toptal | E10: Open — Nigeria eligible | F10: 10+ years | G10: Undisclosed | H10: Bachelor’s degree is required. An MBA or a master’s degree in a relevant field is preferred; 10+ years of B2B commercial experience, including SaaS or services sales to enterprise clients | I10: Lever | J10: 30 Oct | K10: Apply ↗
A11: 6 | B11: Global - Remote / Global - Remote | C11: Senior DevOps & Infrastructure Engineer | D11: Turing | E11: Open — Nigeria eligible | F11: 5+ years | G11: Undisclosed | H11: Independent operational experience in AWS or Azure alongside GCP; Experience with configuration-management tooling such as Ansible, Chef, or Puppet | I11: Greenhouse | J11: 29 Oct | K11: Apply ↗
A12: ▸ Region list incl. Nigeria
A13: 7 | B13: Remote — Africa | C13: Senior IT Implementation Consultant | D13: OpenFn | E13: Open — Nigeria eligible | F13: See posting | G13: Not listed | H13: Full-time contractor; implements data-integration projects for health and NGO clients | I13: Workable | J13: 29 Oct | K13: Apply ↗
A14: ▸ Nigeria-based remote
A15: 8 | B15: Remote — Nigeria | C15: Commercial Aviation & Flight Operations Specialist - AI Projects | D15: Gramian Consulting Group | E15: Open — Nigeria eligible | F15: Not stated | G15: Undisclosed | H15: Hold an Airline Transport Pilot (ATP) certificate, or have relevant qualifications; Have real, hands-on experience with FAA Part 135 operations | I15: Workable | J15: 30 Oct | K15: Apply ↗
A16: 9 | B16: Remote — Nigeria | C16: Forensic Firearms & Toolmark Examination Expert | D16: Gramian Consulting Group | E16: Open — Nigeria eligible | F16: Not stated | G16: Undisclosed | H16: Direct professional experience as a Forensic Firearms and Toolmark Examiner or an equivalent specialist performing firearm; Practical experience with comparison microscopy and the examination of bullets and cartridge cases | I16: Workable | J16: 30 Oct | K16: Apply ↗

Sheet micro1 Referral
A1: micro1 — new roles on your referral link (31 Oct 2026)
A2: Every "Apply ↗" opens that exact micro1 job with your referral code built in.
A4: # | B4: Field | C4: Role | D4: Pay (as listed) | E4: Openings | F4: Posted | G4: Apply via referral | H4: Note
A5: ▸ Engineering Experts
A6: 1 | B6: Engineering Experts | C6: Principal Engineer / Professor — Technical Expert | D6: $85–185/hr | E6: 5 | F6: 31 Oct | G6: Apply ↗ | H6: Aerospace, semiconductors, manufacturing or materials science depth
A7: 2 | B7: Engineering Experts | C7: Manufacturing & Industrial Engineering Expert | D7: $85–185/hr | E7: 5 | F7: 31 Oct | G7: Apply ↗ | H7: Production systems; senior engineering judgment
