Workbook

Sheet Summary
A1: ERJ Remote Job Search Sheet — 26 Oct 2026
A2: Roles posted or first appearing from 23 Oct (including those that showed up after the 23 Oct sheet was made) to 26 Oct · fully remote · open to Nigeria · no repeated links
A4: Tab | B4: Open — Nigeria eligible | C4: Check before applying | D4: Total
A5: Customer Support | B5: =COUNTIF('Customer Support'!$E$5:$E$6,"Open*") -> 1 | C5: =COUNTIF('Customer Support'!$E$5:$E$6,"Check*") -> 0 | D5: =B5+C5 -> 1
A6: VA & Admin | B6: =COUNTIF('VA & Admin'!$E$5:$E$10,"Open*") -> 5 | C6: =COUNTIF('VA & Admin'!$E$5:$E$10,"Check*") -> 0 | D6: =B6+C6 -> 5
A7: HR & Legal | B7: =COUNTIF('HR & Legal'!$E$5:$E$6,"Open*") -> 1 | C7: =COUNTIF('HR & Legal'!$E$5:$E$6,"Check*") -> 0 | D7: =B7+C7 -> 1
A8: Finance & Accounting | B8: =COUNTIF('Finance & Accounting'!$E$5:$E$6,"Open*") -> 1 | C8: =COUNTIF('Finance & Accounting'!$E$5:$E$6,"Check*") -> 0 | D8: =B8+C8 -> 1
A9: Sales | B9: =COUNTIF(Sales!$E$5:$E$6,"Open*") -> 1 | C9: =COUNTIF(Sales!$E$5:$E$6,"Check*") -> 0 | D9: =B9+C9 -> 1
A10: Marketing & Creative | B10: =COUNTIF('Marketing & Creative'!$E$5:$E$13,"Open*") -> 6 | C10: =COUNTIF('Marketing & Creative'!$E$5:$E$13,"Check*") -> 0 | D10: =B10+C10 -> 6
A11: Tech & Operations | B11: =COUNTIF('Tech & Operations'!$E$5:$E$18,"Open*") -> 11 | C11: =COUNTIF('Tech & Operations'!$E$5:$E$18,"Check*") -> 0 | D11: =B11+C11 -> 11
A12: micro1 Referral | B12: =COUNTA('micro1 Referral'!$G$5:$G$19) -> 10 | C12: 0 | D12: =B12+C12 -> 10
A13: Total | B13: =SUM(B5:B12) -> 36 | C13: =SUM(C5:C12) -> 0 | D13: =SUM(D5:D12) -> 36
A15: Notes
A16: • Rule used: the posting names Nigeria, Africa, or worldwide/anywhere. EMEA-only, plain "Remote" and roles with office days were left out.
A17: • Includes roles posted earlier that only appeared after the 23 Oct sheet was made (mostly Growe Talents, added to the board on 26 Oct, and Hire Overseas / Metabase).
A18: • Growe Talents roles are in the iGaming / online casino industry.
A19: • Openhill Global and 10Alytics: no new roles since 23 Oct (all already shared).
A20: • Left out: micro1 military/defence, intelligence, US-only AI Agent Tester and $7–8/hr staff roles; Growe roles listed Europe-first or Chile-first, and its Finance Specialist (needs 1C software); 20four7VA bilingual (Spanish) role.

Sheet Customer Support
A1: Customer Support — new remote roles open to Nigeria (26 Oct 2026)
A2: Posted or first appeared 23–26 Oct 2026 · fully remote · open to people in Nigeria · no link from any earlier ERJ sheet.
A4: # | B4: Who can apply | C4: Role | D4: Company | E4: Status | F4: Level | G4: Pay (as listed) | H4: Key requirements | I4: Source | J4: Posted | K4: Apply link | L4: Note
A5: ▸ Worldwide / global
A6: 1 | B6: Anywhere / Anywhere | C6: VIP Account Manager | D6: Growe Talents | E6: Open — Nigeria eligible | F6: Not stated | G6: Undisclosed | H6: Previous experience in VIP account management, customer support, sales, or a similar client-facing role; Strong English communication skills - Upper Intermediate level | I6: Greenhouse | J6: 23 Oct | K6: Apply ↗ | L6: iGaming / online casino industry

Sheet VA & Admin
A1: VA & Admin — new remote roles open to Nigeria (26 Oct 2026)
A2: Posted or first appeared 23–26 Oct 2026 · fully remote · open to people in Nigeria · no link from any earlier ERJ sheet.
A4: # | B4: Who can apply | C4: Role | D4: Company | E4: Status | F4: Level | G4: Pay (as listed) | H4: Key requirements | I4: Source | J4: Posted | K4: Apply link | L4: Note
A5: ▸ Worldwide / global
A6: 1 | B6: Worldwide | C6: Credit Consultation & Client Engagement Virtual Assistant | D6: 20four7VA | E6: Open — Nigeria eligible | F6: Not stated | G6: Undisclosed | H6: Experience reading and understanding consumer credit reports strongly preferred; Excellent spoken and written English required | I6: Breezy | J6: 23 Oct | K6: Apply ↗
A7: 2 | B7: Worldwide | C7: Customer Success & Sales Operations Administrative Virtual Assistant | D7: 20four7VA | E7: Open — Nigeria eligible | F7: 2+ years | G7: Undisclosed | H7: 2+ years of administrative, operations, or executive support experience required; Strong Google Sheets and/or Microsoft Excel experience required | I7: Breezy | J7: 23 Oct | K7: Apply ↗
A8: 3 | B8: Worldwide | C8: Inbound Customer Service & Dispatch Scheduling Virtual Assistant | D8: 20four7VA | E8: Open — Nigeria eligible | F8: Not stated | G8: Undisclosed | H8: Previous inbound call-handling or customer-service experience required; Excellent spoken English required | I8: Breezy | J8: 23 Oct | K8: Apply ↗
A9: 4 | B9: Worldwide | C9: Social Media Content Creator & On-Camera Talent Virtual Assistant | D9: 20four7VA | E9: Open — Nigeria eligible | F9: Not stated | G9: Undisclosed | H9: Previous experience in content creation, social media video production, or a similar role; Experience with creating viral hooks for social media and short-form video content | I9: Breezy | J9: 23 Oct | K9: Apply ↗
A10: 5 | B10: Worldwide | C10: Walmart WFS Product Sourcing & E-Commerce Virtual Assistant | D10: 20four7VA | E10: Open — Nigeria eligible | F10: Not stated | G10: Undisclosed | H10: Previous Walmart Marketplace/WFS experience preferred; Walmart product sourcing experience preferred | I10: Breezy | J10: 23 Oct | K10: Apply ↗

Sheet HR & Legal
A1: HR & Legal — new remote roles open to Nigeria (26 Oct 2026)
A2: Posted or first appeared 23–26 Oct 2026 · fully remote · open to people in Nigeria · no link from any earlier ERJ sheet.
A4: # | B4: Who can apply | C4: Role | D4: Company | E4: Status | F4: Level | G4: Pay (as listed) | H4: Key requirements | I4: Source | J4: Posted | K4: Apply link | L4: Note
A5: ▸ Worldwide / global
A6: 1 | B6: Remote / Global | C6: Director, Talent Management | D6: GiveDirectly | E6: Open — Nigeria eligible | F6: 7+ years | G6: Undisclosed | H6: 7+ years in talent management, performance, or organizational design roles, including time leading a function or a major part of one; You have designed a performance system, not only administered one | I6: Greenhouse | J6: 25 Oct | K6: Apply ↗

Sheet Finance & Accounting
A1: Finance & Accounting — new remote roles open to Nigeria (26 Oct 2026)
A2: Posted or first appeared 23–26 Oct 2026 · fully remote · open to people in Nigeria · no link from any earlier ERJ sheet.
A4: # | B4: Who can apply | C4: Role | D4: Company | E4: Status | F4: Level | G4: Pay (as listed) | H4: Key requirements | I4: Source | J4: Posted | K4: Apply link | L4: Note
A5: ▸ Region list incl. Nigeria
A6: 1 | B6: Egypt / Argentina / Ethiopia / South Africa / Nigeria | C6: Project Finance Coordinator | D6: Scale Army | E6: Open — Nigeria eligible | F6: 2+ years | G6: $2K – $2.6K per month | H6: Strong proficiency in Microsoft Excel and Google Sheets, including maintaining accurate financial trackers, budgets, and reports; Working knowledge of Accounts Receivable processes, including invoicing schedules, payment tracking, and collections | I6: Ashby | J6: 23 Oct | K6: Apply ↗

Sheet Sales
A1: Sales — new remote roles open to Nigeria (26 Oct 2026)
A2: Posted or first appeared 23–26 Oct 2026 · fully remote · open to people in Nigeria · no link from any earlier ERJ sheet.
A4: # | B4: Who can apply | C4: Role | D4: Company | E4: Status | F4: Level | G4: Pay (as listed) | H4: Key requirements | I4: Source | J4: Posted | K4: Apply link | L4: Note
A5: ▸ Region list incl. Nigeria
A6: 1 | B6: Egypt / Argentina / Ethiopia / South Africa / Nigeria | C6: Sales Executive | D6: Scale Army | E6: Open — Nigeria eligible | F6: 3+ years | G6: $2K per month • Offers Commission | H6: Exceptional spoken English with strong clarity and articulation; Strong listening skills and natural conversational ability | I6: Ashby | J6: 23 Oct | K6: Apply ↗

Sheet Marketing & Creative
A1: Marketing & Creative — new remote roles open to Nigeria (26 Oct 2026)
A2: Posted or first appeared 23–26 Oct 2026 · fully remote · open to people in Nigeria · no link from any earlier ERJ sheet.
A4: # | B4: Who can apply | C4: Role | D4: Company | E4: Status | F4: Level | G4: Pay (as listed) | H4: Key requirements | I4: Source | J4: Posted | K4: Apply link | L4: Note
A5: ▸ Worldwide / global
A6: 1 | B6: Anywhere; Europe / Anywhere | C6: Brand Manager | D6: Growe Talents | E6: Open — Nigeria eligible | F6: 2+ years | G6: Undisclosed | H6: 2+ years of experience in the iGaming industry; Experience managing an entire casino/sportsbook brand or overseeing brand operations within an online gaming company | I6: Greenhouse | J6: 9 Oct | K6: Apply ↗ | L6: iGaming / online casino industry
A7: 2 | B7: Anywhere; Europe / Anywhere | C7: UI/UX Designer (IGaming) | D7: Growe Talents | E7: Open — Nigeria eligible | F7: 3+ years | G7: Undisclosed | H7: 3+ years of experience in UX/UI or Product Design, preferably within iGaming, gaming, or other digital product environments; Strong understanding of UX principles, user behavior, and interaction design, ideally within real-money iGaming | I7: Greenhouse | J7: 12 Oct | K7: Apply ↗ | L7: iGaming / online casino industry
A8: ▸ Region list incl. Nigeria
A9: 3 | B9: Egypt / Argentina / Ethiopia / South Africa / Nigeria | C9: Influencer Marketing Specialist | D9: Scale Army | E9: Open — Nigeria eligible | F9: 3–4 years | G9: $1.4K – $2K per month | H9: Strong relationship-building and negotiation skills with the ability to confidently communicate with creators, influencers; Strong understanding of Instagram influencer marketing and familiarity with the TikTok creator ecosystem | I9: Ashby | J9: 23 Oct | K9: Apply ↗
A10: 4 | B10: Egypt / Argentina / Ethiopia / South Africa / Nigeria | C10: Media Buyer & Creative Strategist | D10: Scale Army | E10: Open — Nigeria eligible | F10: Not stated | G10: $2.3K – $2.5K per month | H10: Strong understanding of paid acquisition strategies, audience targeting, campaign optimization, and performance reporting; Ability to independently launch, manage, and optimize advertising campaigns across Meta and Google Ads | I10: Ashby | J10: 23 Oct | K10: Apply ↗
A11: 5 | B11: Egypt / Argentina / Ethiopia / South Africa / Nigeria | C11: Wellness Creative Designer | D11: Scale Army | E11: Open — Nigeria eligible | F11: 3–4 years | G11: $1.5K – $1.7K per month | H11: 3–4 years of professional experience in graphic design, digital design, content creation, or a related creative role; Must have experience in the wellness and/or food industry | I11: Ashby | J11: 23 Oct | K11: Apply ↗
A12: ▸ Nigeria-based remote
A13: 6 | B13: Remote — Lagos, Nigeria | C13: Creative Designer (BBS879) | D13: Hire Overseas | E13: Open — Nigeria eligible | F13: Not stated | G13: Undisclosed | H13: Proven design experience with a portfolio showing finished work across multiple formats including paid ad creative, social content; Proficiency in Figma and Adobe Creative Suite including Illustrator, Photoshop, and InDesign | I13: Workable | J13: 15 Oct | K13: Apply ↗

Sheet Tech & Operations
A1: Tech & Operations — new remote roles open to Nigeria (26 Oct 2026)
A2: Posted or first appeared 23–26 Oct 2026 · fully remote · open to people in Nigeria · no link from any earlier ERJ sheet.
A4: # | B4: Who can apply | C4: Role | D4: Company | E4: Status | F4: Level | G4: Pay (as listed) | H4: Key requirements | I4: Source | J4: Posted | K4: Apply link | L4: Note
A5: ▸ Worldwide / global
A6: 1 | B6: Anywhere in the World | C6: Lead Product Management | D6: Carrot | E6: Open — Nigeria eligible | F6: 5+ years | G6: $168,000-$198,000. | H6: A track record of owning complex, cross-functional product initiatives from strategy through execution; Strong product sense and the ability to balance user needs, business goals, and technical constraints in your decision-making | I6: We Work Remotely | J6: 24 Oct | K6: Apply ↗
A7: 2 | B7: Anywhere / Anywhere | C7: Affiliate Manager | D7: Growe Talents | E7: Open — Nigeria eligible | F7: 1+ year | G7: Undisclosed | H7: 1+ year of experience as an Affiliate Manager in the iGaming industry; Understanding of web analytics fundamentals and key traffic performance metrics (ROI, ROMI, eCPA, ARPU) | I7: Greenhouse | J7: 1 Oct | K7: Apply ↗ | L7: iGaming / online casino industry
A8: 3 | B8: Anywhere / Anywhere | C8: Casino Manager (Sportsbook Experience) | D8: Growe Talents | E8: Open — Nigeria eligible | F8: Not stated | G8: Undisclosed | H8: Experience working in online sportsbook operations or a related sports betting role; Strong understanding of sportsbook mechanics, betting markets, odds, margin, and the sports calendar | I8: Greenhouse | J8: 23 Oct | K8: Apply ↗ | L8: iGaming / online casino industry
A9: 4 | B9: Anywhere; Europe / Anywhere | C9: Product Manager (IGaming) | D9: Growe Talents | E9: Open — Nigeria eligible | F9: 2+ years | G9: Undisclosed | H9: 2+ years of experience in Product or Technical Project Management, including hands-on delivery of software development projects; Proven experience in real-money iGaming, with a strong understanding of casino mechanics and the operator-provider ecosystem | I9: Greenhouse | J9: 12 Oct | K9: Apply ↗ | L9: iGaming / online casino industry
A10: 5 | B10: Anywhere; Europe / Anywhere | C10: Product manager | D10: Growe Talents | E10: Open — Nigeria eligible | F10: Not stated | G10: Undisclosed | H10: Have experience working with B2C IGaming products in performance-oriented environments; Demonstrate strong analytical skills and hands-on work with product and growth metrics (retention, conversion, DAU/MAU, LTV, ARPU) | I10: Greenhouse | J10: 16 Oct | K10: Apply ↗ | L10: iGaming / online casino industry
A11: 6 | B11: Global Remote | C11: Security Engineer | D11: Metabase | E11: Open — Nigeria eligible | F11: Not stated | G11: Undisclosed | H11: A demonstrated track record of finding and exploiting application vulnerabilities through source code analysis and hands-on research; The ability to independently navigate unfamiliar codebases, understand complex architectures, and reason about runtime behavio | I11: Lever | J11: 14 Oct | K11: Apply ↗
A12: 7 | B12: Remote, Global | C12: Data API Engineer | D12: Supabase | E12: Open — Nigeria eligible | F12: 3+ years | G12: Undisclosed | H12: Strong Haskell skills with at least 3 years of experience; Experience using the C language | I12: Ashby | J12: 24 Oct | K12: Apply ↗
A13: 8 | B13: Remote, Global | C13: Software Engineer - Storage | D13: Supabase | E13: Open — Nigeria eligible | F13: 5+ years | G13: Undisclosed | H13: Prior experience working on developer tools; Solid knowledge of cloud infrastructure (AWS, GCP or Azure) and containerization (Docker, Kubernetes) | I13: Ashby | J13: 24 Oct | K13: Apply ↗
A14: ▸ Region list incl. Nigeria
A15: 9 | B15: Remote — anywhere in Africa | C15: Data Quality Analyst | D15: Imagine Worldwide | E15: Open — Nigeria eligible | F15: See posting | G15: Not listed | H15: Full-time remote; data quality for education programmes; overlap with Africa working hours | I15: Greenhouse | J15: 23 Oct | K15: Apply ↗
A16: 10 | B16: Egypt / Argentina / Ethiopia / South Africa / Nigeria | C16: Email & SMS Automation Specialist | D16: Scale Army | E16: Open — Nigeria eligible | F16: 2–4 years | G16: $2.2K – $2.5K per month | H16: 2–4+ years of experience in email marketing and SMS marketing; Strong hands-on experience with Klaviyo or a comparable email/SMS marketing platform | I16: Ashby | J16: 23 Oct | K16: Apply ↗
A17: ▸ Nigeria-based remote
A18: 11 | B18: Nigeria | C18: Data Platform Engineer (Mid-level) | D18: Jobgether partner | E18: Open — Nigeria eligible | F18: Not stated | G18: €33,000 to €43,000 | H18: Improve CI/CD pipelines; Develop infrastructure-as-code | I18: Lever | J18: 23 Oct | K18: Apply ↗

Sheet micro1 Referral
A1: micro1 — new roles on your referral link (26 Oct 2026)
A2: Every "Apply ↗" opens that exact micro1 job with your referral code built in.
A4: # | B4: Field | C4: Role | D4: Pay (as listed) | E4: Openings | F4: Posted | G4: Apply via referral | H4: Note
A5: ▸ HR & Recruiting
A6: 1 | B6: HR & Recruiting | C6: HR & People Operations Expert | D6: $45–90/hr | E6: 20 | F6: 24 Oct | G6: Apply ↗ | H6: Payroll and people-ops work turned into AI tasks
A7: ▸ Finance
A8: 2 | B8: Finance | C8: Finance & Accounting Expert | D8: $40–90/hr | E8: 20 | F8: 24 Oct | G8: Apply ↗ | H8: Remote, global; reconciliation and error diagnosis
A9: 3 | B9: Finance | C9: Procurement & Vendor Management Expert | D9: $45–90/hr | E9: 20 | F9: 24 Oct | G9: Apply ↗ | H9: Supplier evaluation and selection
A10: ▸ Legal
A11: 4 | B11: Legal | C11: Legal & Compliance Expert | D11: $45–90/hr | E11: 20 | F11: 24 Oct | G11: Apply ↗ | H11: Contract and document review, compliance
A12: ▸ AI Training & Admin
A13: 5 | B13: AI Training & Admin | C13: Business Operations Expert | D13: $45–90/hr | E13: 20 | F13: 24 Oct | G13: Apply ↗ | H13: Business operations experience
A14: 6 | B14: AI Training & Admin | C14: Transportation and Warehousing Expert | D14: $30–70/hr | E14: 30 | F14: 24 Oct | G14: Apply ↗ | H14: Logistics, supply chain
A15: 7 | B15: AI Training & Admin | C15: Sales / Revenue / CS Operations Expert | D15: $40–85/hr | E15: 10 | F15: 24 Oct | G15: Apply ↗ | H15: CRM ownership, revenue tools
A16: 8 | B16: AI Training & Admin | C16: Revenue Operations Specialist (SaaS) | D16: $50–100/hr | E16: 40 | F16: 24 Oct | G16: Apply ↗ | H16: CRM data model, policy arbitration
A17: ▸ Software & Data
A18: 9 | B18: Software & Data | C18: Rust Architect / Backend Developer | D18: See posting | E18: 10 | F18: 24 Oct | G18: Apply ↗ | H18: Production Rust, backend architecture
A19: 10 | B19: Software & Data | C19: Applied Scientists — Machine Learning (MSc. or PhD) | D19: $60–120/hr | E19: 100 | F19: 23 Oct | G19: Apply ↗ | H19: Global, fully remote; ~15 hrs/week
