Workbook

Sheet Summary
A1: ERJ Remote Job Search Sheet — 10 Oct 2026
A2: Posted or first seen 8–10 Oct · nothing from any earlier ERJ sheet (23 Sep → 8 Oct) · priority on thin fields and language/teaching work · company pages only, no gated boards
A4: Tab | B4: Open — Nigeria eligible | C4: Check before applying | D4: Total
A5: Customer Support | B5: =COUNTIF('Customer Support'!$E$5:$E$10,"Open*") -> 5 | C5: =COUNTIF('Customer Support'!$E$5:$E$10,"Check*") -> 0 | D5: =B5+C5 -> 5
A6: VA & Admin | B6: =COUNTIF('VA & Admin'!$E$5:$E$9,"Open*") -> 3 | C6: =COUNTIF('VA & Admin'!$E$5:$E$9,"Check*") -> 0 | D6: =B6+C6 -> 3
A7: HR & Legal | B7: =COUNTIF('HR & Legal'!$E$5:$E$20,"Open*") -> 13 | C7: =COUNTIF('HR & Legal'!$E$5:$E$20,"Check*") -> 0 | D7: =B7+C7 -> 13
A8: Languages & Teaching | B8: =COUNTIF('Languages & Teaching'!$E$5:$E$7,"Open*") -> 2 | C8: =COUNTIF('Languages & Teaching'!$E$5:$E$7,"Check*") -> 0 | D8: =B8+C8 -> 2
A9: Finance & Accounting | B9: =COUNTIF('Finance & Accounting'!$E$5:$E$24,"Open*") -> 17 | C9: =COUNTIF('Finance & Accounting'!$E$5:$E$24,"Check*") -> 0 | D9: =B9+C9 -> 17
A10: Sales & Marketing | B10: =COUNTIF('Sales & Marketing'!$E$5:$E$13,"Open*") -> 7 | C10: =COUNTIF('Sales & Marketing'!$E$5:$E$13,"Check*") -> 0 | D10: =B10+C10 -> 7
A11: Creative & Content | B11: =COUNTIF('Creative & Content'!$E$5:$E$17,"Open*") -> 10 | C11: =COUNTIF('Creative & Content'!$E$5:$E$17,"Check*") -> 0 | D11: =B11+C11 -> 10
A12: Tech & Operations | B12: =COUNTIF('Tech & Operations'!$E$5:$E$24,"Open*") -> 17 | C12: =COUNTIF('Tech & Operations'!$E$5:$E$24,"Check*") -> 0 | D12: =B12+C12 -> 17
A13: micro1 Referral | B13: =COUNTA('micro1 Referral'!$C$5:$C$19) -> 11 | C13: 0 | D13: =B13+C13 -> 11
A14: Total | B14: =SUM(B5:B13) -> 85 | C14: =SUM(C5:C13) -> 0 | D14: =SUM(D5:D13) -> 85
A16: Notes
A17: • Every row is FULLY remote and open to people living in Nigeria: the posting names Nigeria, or says Worldwide / Anywhere / Africa / EMEA (which includes Nigeria). Anything that said only "Remote" with no country, needed US/UK/EU work rights, a US licence, or a foreign language was removed.
A18: • Wider net this round: Canonical, Automattic, Alpaca, Oyster, Moniepoint, M-KOPA, OpenFn, ALX Africa, Renmoney, Helium Health, Huzzle, 20four7VA, Social Discovery Group, AtlasBrands, Minerva, UNEP, Gigmo, Gramian, Brainbase plus Scale Army, TalentPop, Remotasks and micro1. Each job page opened and confirmed live on 10 Oct.
A19: • Thin fields now covered: customer support, VA/admin, HR, legal, finance/bookkeeping and teaching. EMEA rows (Canonical, Oyster, Alpaca) cover Europe, Middle East and Africa; Canonical runs 2–4 paid company events a year.
A20: • Yoruba / Igbo / Hausa: no new openings since 8 Oct; the 8 Oct Languages tab roles are still live.
A21: • Removed after checking: Wikimedia, Mozilla, GitLab, Khan Academy, Zapier, Kraken (country lists exclude Nigeria); RateHawk, Faculty Online, Mindrift, LILT gaming roles (no country list); Automattic VIP support (US citizens); Pearl, Voxidea (LatAm only); Stay Group (gambling); micro1 US-licensed medical/legal roles.

Sheet Customer Support
A1: Customer Support — new remote roles open to Nigeria (10 Oct 2026)
A2: From company career pages (Ashby, Greenhouse, Lever, Workable) and official teaching platforms. Nothing here appears on any earlier ERJ sheet.
A4: # | B4: Who can apply | C4: Role | D4: Company | E4: Status | F4: Level | G4: Pay (as listed) | H4: Key requirements | I4: ATS | J4: Posted | K4: Apply link | L4: Note
A5: ▸ Worldwide / global
A6: 1 | B6: Worldwide; "REGION PREFERENCES: Any" | C6: CS1 Patient Onboarding Agent (Customer Support) — CPT-11597 | D6: 20four7VA | E6: Open — Nigeria eligible | F6: Entry–Mid | G6: Not listed ("competitive rates, weekly payments") | H6: 1+ yr customer/patient/call-centre support; de-escalation; neutral English accent; 40 hrs/wk 9am–6pm PST | I6: Breezy HR | J6: 08 Oct 2026 | K6: Apply ↗ | L6: Independent contractor; includes weekend shifts
A7: 2 | B7: Worldwide; "REGION PREFERENCES: Any" | C7: Operations & Customer Support Virtual Assistant — CPT-11573 | D7: 20four7VA | E7: Open — Nigeria eligible | F7: Entry–Mid | G7: Not listed ("competitive rates, weekly payments") | H7: Customer service + CRM experience; strong phone skills; native/near-native English accent; 15 hrs/wk M/W/F | I7: Breezy HR | J7: 06 Oct 2026 | K7: Apply ↗ | L7: Part-time contractor
A8: 3 | B8: Remote — fully remote company (no country restriction stated) | C8: Director of Professional Services, WordPress VIP | D8: Automattic | E8: Open — Nigeria eligible | F8: Director | G8: $130,000–$190,000 USD | H8: 8+ yrs leading professional services/implementation; enterprise SaaS delivery; services portfolio building | I8: Greenhouse | J8: 2 Oct | K8: Apply ↗ | L8: Reports to VP Customer Experience
A9: 4 | B9: Home based — Worldwide | C9: Associate Linux Support Engineer | D9: Canonical | E9: Open — Nigeria eligible | F9: Entry (Associate) | G9: Not listed | H9: Linux troubleshooting; 2+ of sysadmin/programming/networking/cloud; strong English | I9: Greenhouse | J9: Aug–Oct 2026 | K9: Apply ↗ | L9: Weekend rotation; travel 2x a year
A10: 5 | B10: "Worldwide" / "Remote Worldwide" | C10: Senior Product Analyst (CX) | D10: Social Discovery Group | E10: Open — Nigeria eligible | F10: Senior | G10: Not listed | H10: Maths/technical degree; deep A/B-testing and product analytics experience | I10: Breezy HR | J10: 07 Oct 2026 | K10: Apply ↗

Sheet VA & Admin
A1: VA & Admin — new remote roles open to Nigeria (10 Oct 2026)
A2: From company career pages (Ashby, Greenhouse, Lever, Workable) and official teaching platforms. Nothing here appears on any earlier ERJ sheet.
A4: # | B4: Who can apply | C4: Role | D4: Company | E4: Status | F4: Level | G4: Pay (as listed) | H4: Key requirements | I4: ATS | J4: Posted | K4: Apply link | L4: Note
A5: ▸ Worldwide / global
A6: 1 | B6: Worldwide; "REGION PREFERENCES: Any" | C6: Executive Administrative & Research Virtual Assistant — CPT-11608 | D6: 20four7VA | E6: Open — Nigeria eligible | F6: Mid | G6: Not listed ("competitive rates, weekly payments") | H6: 2+ yrs admin/EA/operations; CRM skills; excellent written English; ~10 hrs/wk PT hours | I6: Breezy HR | J6: 05 Oct 2026 | K6: Apply ↗ | L6: Part-time contractor
A7: ▸ Region list incl. Nigeria
A8: 2 | B8: Home based — EMEA | C8: Executive Assistant / Corporate Administrator | D8: Canonical | E8: Open — Nigeria eligible | F8: Entry / Junior | G8: Not listed | H8: Business or technical degree; strong communication; travel up to 4x a year | I8: Greenhouse | J8: Oct 2026 | K8: Apply ↗ | L8: Not seeking extensive experience — good early-career role
A9: 3 | B9: "This position will be remote and based in Nigeria" | C9: NiMERP Project Coordinator and MARS Engagement Support (Consultant) | D9: UNEP (United Nations Environment Programme) | E9: Open — Nigeria eligible | F9: Senior | G9: Not listed (UN consultancy fee) | H9: Master's + 5 yrs relevant experience incl. work with Nigerian government agencies; English | I9: UN Careers (Inspira) | J9: 07 Oct 2026 | K9: Apply ↗ | L9: Job opening 285931; 12-month consultancy; deadline 15 Oct 2026

Sheet HR & Legal
A1: HR & Legal — new remote roles open to Nigeria (10 Oct 2026)
A2: From company career pages (Ashby, Greenhouse, Lever, Workable) and official teaching platforms. Nothing here appears on any earlier ERJ sheet.
A4: # | B4: Who can apply | C4: Role | D4: Company | E4: Status | F4: Level | G4: Pay (as listed) | H4: Key requirements | I4: ATS | J4: Posted | K4: Apply link | L4: Note
A5: ▸ Worldwide / global
A6: 1 | B6: Worldwide; "REGION PREFERENCES: Any" | C6: Legal Administrative Virtual Assistant — CPT-11320 | D6: 20four7VA | E6: Open — Nigeria eligible | F6: Entry–Mid | G6: Not listed ("competitive rates, weekly payments") | H6: 1–3+ yrs admin/VA experience; professional phone manner; native/near-native English; 20 hrs/wk EST | I6: Breezy HR | J6: 24 Sep 2026 | K6: Apply ↗ | L6: Part-time contractor; no licence required
A7: 2 | B7: "Worldwide / Spain / Poland / Portugal / Serbia" (remote) | C7: Executive Search Partner | D7: Social Discovery Group | E7: Open — Nigeria eligible | F7: Senior | G7: Not listed | H7: 5–7 yrs hands-on executive search; closed mid-senior/executive tech roles; EMEA recruiting | I7: Breezy HR | J7: 01 Oct 2026 | K7: Apply ↗
A8: ▸ Region list incl. Nigeria
A9: 3 | B9: Remote — EMEA | C9: People Operations Partner | D9: Alpaca | E9: Open — Nigeria eligible | F9: Junior–Mid (1-3 yrs) | G9: Not listed (+ stock options, $150/mo stipend) | H9: 1-3 yrs People/HR Ops; employee lifecycle admin; multi-country workforce comfort | I9: Greenhouse | J9: 19 Sep | K9: Apply ↗ | L9: Works across time zones
A10: 4 | B10: Home based — EMEA | C10: Executive Search Lead — Technology | D10: Canonical | E10: Open — Nigeria eligible | F10: Senior | G10: Not listed | H10: Senior tech executive-search experience; SQL or Python for analysis; behavioural interviewing | I10: Greenhouse | J10: Oct 2026 | K10: Apply ↗
A11: 5 | B11: Home based — Americas or EMEA | C11: HR Generalist | D11: Canonical | E11: Open — Nigeria eligible | F11: Mid | G11: Not listed | H11: HR qualification; working knowledge of EMEA or Americas employment law; travel up to 4x a year | I11: Greenhouse | J11: Oct 2026 | K11: Apply ↗
A12: 6 | B12: Home based — Americas or EMEA (or London office) | C12: Legal Counsel — Regulatory Compliance, Product & Privacy | D12: Canonical | E12: Open — Nigeria eligible | F12: Legal Advisor / Counsel | G12: Not listed | H12: Law degree + active (or in-progress) practising licence, any jurisdiction; compliance/privacy exposure; excellent English drafting | I12: Greenhouse | J12: Oct 2026 | K12: Apply ↗ | L12: No specific bar jurisdiction required
A13: 7 | B13: Home based — Americas or EMEA | C13: Organisational Development Associate | D13: Canonical | E13: Open — Nigeria eligible | F13: Early career (≤2 yrs post-grad) | G13: Not listed | H13: Early leadership/organising record; interest in org psychology/behavioural science; coachable | I13: Greenhouse | J13: Oct 2026 | K13: Apply ↗
A14: 8 | B14: Remote: India, Kenya, Lagos (Nigeria), Pakistan, Poland, South Africa, Spain | C14: Engineering Relations Partner | D14: Moniepoint | E14: Open — Nigeria eligible | F14: Mid-Senior | G14: Not listed | H14: Ex-software engineer; fintech/high-scale background; strong technical writing | I14: Greenhouse | J14: Live Oct 2026 | K14: Apply ↗ | L14: Engineering employer-brand/talent role; posting says 'fully remote environment'
A15: 9 | B15: Location "EMEA"; "all of Oyster's positions are fully remote"; 3–4 hrs CET overlap | C15: Legal Counsel (Employment Products) | D15: Oyster HR | E15: Open — Nigeria eligible | F15: Mid–Senior | G15: Not listed | H15: Law degree + admission in any jurisdiction; 4+ yrs employment law | I15: Ashby | J15: 26 Jun 2026 | K15: Apply ↗ | L15: Older posting but still open; must be authorised to work where you live
A16: ▸ Nigeria-based remote
A17: 10 | B17: Remote, Lagos, Nigeria | C17: Early Careers Talent Acquisition Specialist | D17: Moniepoint | E17: Open — Nigeria eligible | F17: Mid (5-7 yrs) | G17: Not listed | H17: 5-7 yrs recruiting, ideally campus/graduate hiring; multi-stakeholder coordination; ATS tools | I17: Greenhouse | J17: 22 Sep | K17: Apply ↗ | L17: Listed as Remote with Lagos tag
A18: 11 | B18: Remote, Lagos, Nigeria | C18: Fraud Investigation Officer | D18: Moniepoint | E18: Open — Nigeria eligible | F18: Junior-Mid (2-4 yrs) | G18: Not listed | H18: Degree; 2-4 yrs fraud investigation/banking/fintech risk; transaction analysis | I18: Greenhouse | J18: Live Oct 2026 | K18: Apply ↗
A19: 12 | B19: Remote, Nigeria | C19: Security & Technology Risk Analyst | D19: Moniepoint | E19: Open — Nigeria eligible | F19: Mid-Senior (5+ yrs) | G19: Not listed | H19: 5+ yrs operational/cyber/tech risk; risk assessments; KPI dashboards for execs | I19: Greenhouse | J19: Live Oct 2026 | K19: Apply ↗
A20: 13 | B20: Remote, Lagos, Nigeria | C20: Talent Acquisition Specialist | D20: Moniepoint | E20: Open — Nigeria eligible | F20: Mid–Senior (5+ yrs) | G20: Not listed (pension, HMO, annual bonus) | H20: 5+ yrs full-cycle recruiting; HR/technical education; agency + in-house, tech & non-tech hiring | I20: Greenhouse | J20: 31 Aug | K20: Apply ↗ | L20: Listed as Remote with Lagos tag

Sheet Languages & Teaching
A1: Languages & Teaching — new remote roles open to Nigeria (10 Oct 2026)
A2: From company career pages (Ashby, Greenhouse, Lever, Workable) and official teaching platforms. Nothing here appears on any earlier ERJ sheet.
A4: # | B4: Who can apply | C4: Role | D4: Company | E4: Status | F4: Level | G4: Pay (as listed) | H4: Key requirements | I4: ATS | J4: Posted | K4: Apply link | L4: Note
A5: ▸ Nigeria-based remote
A6: 1 | B6: Nigeria-based (remote) | C6: AI Trainers Network - English | D6: Jobgether (for Welo Data) | E6: Open — Nigeria eligible | F6: Entry level | G6: Per project | H6: Native/near-native English; annotate and rate AI answers, write prompts | I6: Lever | J6: Oct 2026 | K6: Apply ↗
A7: 2 | B7: Nigeria-based (remote) | C7: E-Learning Instructional Designer | D7: Jobgether (partner company) | E7: Open — Nigeria eligible | F7: 2+ yrs | G7: Not listed | H7: 6-month contract; Mon–Fri on Australian (AEST) hours; Articulate, LMS, SCORM | I7: Lever | J7: Oct 2026 | K7: Apply ↗

Sheet Finance & Accounting
A1: Finance & Accounting — new remote roles open to Nigeria (10 Oct 2026)
A2: From company career pages (Ashby, Greenhouse, Lever, Workable) and official teaching platforms. Nothing here appears on any earlier ERJ sheet.
A4: # | B4: Who can apply | C4: Role | D4: Company | E4: Status | F4: Level | G4: Pay (as listed) | H4: Key requirements | I4: ATS | J4: Posted | K4: Apply link | L4: Note
A5: ▸ Worldwide / global
A6: 1 | B6: Worldwide; "REGION PREFERENCES: Any" | C6: Accounting, Bookkeeping & Operations Virtual Assistant — CPT-11564 | D6: 20four7VA | E6: Open — Nigeria eligible | F6: Mid | G6: Not listed ("competitive rates, weekly payments") | H6: Bookkeeping + QuickBooks Multi-Currency; strong Excel; 20 hrs/wk incl. 4–7pm EST | I6: Breezy HR | J6: 04 Oct 2026 | K6: Apply ↗ | L6: Part-time contractor
A7: 2 | B7: Worldwide; "REGION PREFERENCES: Any" | C7: Finance & Tax Support Virtual Assistant — CPT-11624 | D7: 20four7VA | E7: Open — Nigeria eligible | F7: Mid | G7: Not listed ("competitive rates, weekly payments") | H7: Strong QuickBooks; financial tracking & reporting; good written English; 10 hrs/wk PT | I7: Breezy HR | J7: 07 Oct 2026 | K7: Apply ↗ | L7: No CPA/EA required
A8: 3 | B8: "Remote - Worldwide" (4+ hrs overlap 9am–5pm EST) | C8: Accounting Manager | D8: AtlasBrands | E8: Open — Nigeria eligible | F8: Senior | G8: $5,000–$8,000/month | H8: 5+ yrs accounting incl. multi-entity parent co; DTC/e-commerce; QuickBooks Online; managed a bookkeeper | I8: Breezy HR | J8: 09 Oct 2026 | K8: Apply ↗
A9: 4 | B9: "Worldwide / Warsaw / Belgrade / Tbilisi / Yerevan" (remote) | C9: Accounting Manager | D9: Social Discovery Group | E9: Open — Nigeria eligible | F9: Senior | G9: Not listed | H9: 3+ yrs senior/GL accountant in multi-entity intl company; IFRS and/or US GAAP; B2+ English | I9: Breezy HR | J9: 05 Oct 2026 | K9: Apply ↗
A10: ▸ Region list incl. Nigeria
A11: 5 | B11: Home based — EMEA (EMEA time zones) | C11: Accountant | D11: Canonical | E11: Open — Nigeria eligible | F11: Mid | G11: Not listed | H11: Accounting degree; ACCA/ACA/CPA or similar qualification; IFRS expertise | I11: Greenhouse | J11: Aug–Oct 2026 | K11: Apply ↗ | L11: In-person company events 2-4x a year (travel paid)
A12: 6 | B12: Home based — EMEA (or London office) | C12: Accounts Payable Clerk | D12: Canonical | E12: Open — Nigeria eligible | F12: Entry–Mid | G12: Not listed | H12: Accounting/finance education; strong Excel; organised and deadline-driven | I12: Greenhouse | J12: 2 Oct | K12: Apply ↗ | L12: AI-written applications disqualified; In-person company events 2-4x a year (travel paid)
A13: 7 | B13: Home based — EMEA (remote) | C13: Accounts Receivable Clerk | D13: Canonical | E13: Open — Nigeria eligible | F13: Entry–Mid | G13: Not listed | H13: Accounting/finance education; strong Excel (pivots, lookups); high attention to detail | I13: Greenhouse | J13: 2 Oct | K13: Apply ↗ | L13: In-person company events 2-4x a year (travel paid)
A14: 8 | B14: Home based — EMEA (or London office) | C14: Global Payroll Manager | D14: Canonical | E14: Open — Nigeria eligible | F14: Manager | G14: Not listed | H14: Multi-country payroll experience; payroll compliance & controls; payroll systems + analytics | I14: Greenhouse | J14: Oct 2026 | K14: Apply ↗
A15: 9 | B15: Home based — Americas or EMEA | C15: Global Treasury Analyst | D15: Canonical | E15: Open — Nigeria eligible | F15: Senior | G15: Not listed | H15: Quantitative degree; CTP/CFA-type certification; global treasury experience | I15: Greenhouse | J15: Oct 2026 | K15: Apply ↗
A16: 10 | B16: Home based — EMEA (or London office) | C16: Tax Senior Associate | D16: Canonical | E16: Open — Nigeria eligible | F16: Senior | G16: Not listed | H16: ACA/ACCA/CIMA + CTA/ADIT or equivalent; 3-5 yrs tax at Big 4/Top 10 or multinational | I16: Greenhouse | J16: Oct 2026 | K16: Apply ↗
A17: 11 | B17: Location "EMEA"; "must be based within +3/-3 UTC"; fully remote | C17: Accounts Payable Analyst | D17: Oyster HR | E17: Open — Nigeria eligible | F17: Mid | G17: Not listed | H17: 3+ yrs AP; advanced ERP (NetSuite a plus); advanced Excel/Sheets | I17: Ashby | J17: 08 Oct 2026 | K17: Apply ↗ | L17: Nigeria (UTC+1) is inside the time-zone band
A18: ▸ Nigeria-based remote
A19: 12 | B19: TELECOMMUTE, Nigeria - Remote (UK working hours) | C19: Bookkeeper - Xero Specialist | D19: Huzzle | E19: Open — Nigeria eligible | F19: Mid | G19: Not listed | H19: Hands-on Xero; UK bookkeeping/HMRC; reconciliations, AP/AR | I19: Workable | J19: 28 Sep | K19: Apply ↗ | L19: UK hours
A20: 13 | B20: TELECOMMUTE, Nigeria | C20: Finance Ops / Bookkeeper (part-time) | D20: Huzzle | E20: Open — Nigeria eligible | F20: Mid | G20: Not listed | H20: Expert QuickBooks Online; Canadian payroll/tax knowledge; collections | I20: Workable | J20: 2 Oct | K20: Apply ↗ | L20: Part-time; placed with Huzzle client
A21: 14 | B21: Remote, Nigeria | C21: Financial Planning Analyst | D21: Moniepoint | E21: Open — Nigeria eligible | F21: Mid (4-6 yrs) | G21: Not listed | H21: 4-6 yrs FP&A; advanced Excel/modelling; multi-entity, multi-currency | I21: Greenhouse | J21: Live Oct 2026 | K21: Apply ↗
A22: 15 | B22: Remote, Nigeria | C22: Head, Group FP&A | D22: Moniepoint | E22: Open — Nigeria eligible | F22: Head / Senior leadership | G22: Not listed | H22: 8-10+ yrs FP&A/corp finance/IB; multi-entity, multi-currency consolidation; ACA/ACCA/CFA | I22: Greenhouse | J22: 24 Sep | K22: Apply ↗
A23: 16 | B23: Remote, Nigeria | C23: Head, Product Control & Accounting | D23: Moniepoint | E23: Open — Nigeria eligible | F23: Head / Senior (8+ yrs PQE) | G23: Not listed | H23: ACA/ACCA; Big 4 technical accounting; IFRS 9 & 15 | I23: Greenhouse | J23: Live Oct 2026 | K23: Apply ↗
A24: 17 | B24: Remote, Lagos, Nigeria | C24: Product Auditor | D24: Moniepoint | E24: Open — Nigeria eligible | F24: Mid (3-5+ yrs) | G24: Not listed | H24: 3-5+ yrs product/systems audit; advanced SQL; payments & reconciliation knowledge | I24: Greenhouse | J24: Live Oct 2026 | K24: Apply ↗

Sheet Sales & Marketing
A1: Sales & Marketing — new remote roles open to Nigeria (10 Oct 2026)
A2: From company career pages (Ashby, Greenhouse, Lever, Workable) and official teaching platforms. Nothing here appears on any earlier ERJ sheet.
A4: # | B4: Who can apply | C4: Role | D4: Company | E4: Status | F4: Level | G4: Pay (as listed) | H4: Key requirements | I4: ATS | J4: Posted | K4: Apply link | L4: Note
A5: ▸ Worldwide / global
A6: 1 | B6: Worldwide; "REGION PREFERENCES: Any" | C6: Sales Development & Sales Operations Virtual Assistant — CPT-11531 | D6: 20four7VA | E6: Open — Nigeria eligible | F6: Mid | G6: Not listed ("competitive rates, weekly payments") | H6: B2B outbound prospecting, cold calling, appointment setting, CRM pipeline; native/near-native English; 40 hrs/wk EST | I6: Breezy HR | J6: 04 Oct 2026 | K6: Apply ↗ | L6: Full-time contractor
A7: 2 | B7: Home based — Worldwide | C7: Business Development Representative | D7: Canonical | E7: Open — Nigeria eligible | F7: Mid | G7: Not listed (base + commission) | H7: Proven SDR/outbound record beating quota; enterprise software sales; professional English | I7: Greenhouse | J7: Aug–Oct 2026 | K7: Apply ↗ | L7: Travel 2x a year for company events
A8: ▸ Region list incl. Nigeria
A9: 3 | B9: 'This role is remote, Africa-based' (GMT+1/+2 preferred) | C9: Enterprise Sales Manager | D9: ALX Africa | E9: Open — Nigeria eligible | F9: Senior (8+ yrs) | G9: Base + commission (not listed) | H9: 8+ yrs B2B enterprise sales; 3+ yrs leading people; pipeline building | I9: Greenhouse | J9: Oct 2026 | K9: Apply ↗ | L9: Possible travel to client markets
A10: 4 | B10: Remote — prioritising Americas or Europe / Africa | C10: Senior Revenue Operations Manager | D10: Automattic | E10: Open — Nigeria eligible | F10: Senior IC | G10: $140,000–$200,000 USD (paid in local currency) | H10: 6-8+ yrs RevOps incl. a 0→1 build; strong Salesforce; SQL or Python | I10: Greenhouse | J10: 24 Sep | K10: Apply ↗
A11: 5 | B11: Home based — EMEA | C11: Sales Enablement Manager | D11: Canonical | E11: Open — Nigeria eligible | F11: Senior / Lead | G11: Not listed | H11: MEDDPICC proficiency; built enablement programmes in high-growth markets; travel 2x a year | I11: Greenhouse | J11: Oct 2026 | K11: Apply ↗
A12: 6 | B12: Remote, based in Sub-Saharan Africa (SA, Kenya, Ethiopia, Nigeria, Rwanda, Uganda) | C12: Marketing Director | D12: OpenFn | E12: Open — Nigeria eligible | F12: Director (8+ yrs) | G12: Not listed | H12: 8+ yrs tech marketing; demand gen & pipeline; own website/SEO/analytics | I12: Workable | J12: 10 Sep | K12: Apply ↗
A13: 7 | B13: Egypt, Argentina, Ethiopia, Nigeria, South Africa | C13: SEO & GEO Specialist (Part-time) | D13: Scale Army | E13: Open — Nigeria eligible | F13: See posting | G13: $1k/mo | H13: Part-time contract; SEO + generative-engine (AI search) optimisation | I13: Ashby | J13: Oct 2026 | K13: Apply ↗

Sheet Creative & Content
A1: Creative & Content — new remote roles open to Nigeria (10 Oct 2026)
A2: From company career pages (Ashby, Greenhouse, Lever, Workable) and official teaching platforms. Nothing here appears on any earlier ERJ sheet.
A4: # | B4: Who can apply | C4: Role | D4: Company | E4: Status | F4: Level | G4: Pay (as listed) | H4: Key requirements | I4: ATS | J4: Posted | K4: Apply link | L4: Note
A5: ▸ Worldwide / global
A6: 1 | B6: Worldwide; "REGION PREFERENCES: Any" | C6: Content, Marketing & Travel Operations Virtual Assistant — CPT-11595 | D6: 20four7VA | E6: Open — Nigeria eligible | F6: Entry–Mid | G6: Not listed ("competitive rates, weekly payments") | H6: Social media scheduling/content support; strong written English; 10 hrs/wk flexible | I6: Breezy HR | J6: 09 Oct 2026 | K6: Apply ↗ | L6: Part-time contractor
A7: ▸ Region list incl. Nigeria
A8: 2 | B8: Home based — EMEA | C8: Senior Communications Specialist — Social Media | D8: Canonical | E8: Open — Nigeria eligible | F8: Senior | G8: Not listed | H8: Senior experience across major social platforms; social management/analytics tools; strong prioritisation | I8: Greenhouse | J8: Oct 2026 | K8: Apply ↗
A9: 3 | B9: London; Remote: Nigeria, Poland, Portugal, Spain | C9: Senior Product Designer - Design System | D9: Moniepoint | E9: Open — Nigeria eligible | F9: Senior (3+ yrs) | G9: Not listed | H9: Advanced Figma (tokens, components); fintech/SaaS UX; design systems | I9: Greenhouse | J9: Oct 2026 | K9: Apply ↗ | L9: Marked New on board
A10: 4 | B10: Egypt, Argentina, Ethiopia, Nigeria, South Africa | C10: Graphic Design & Social Media Specialist | D10: Scale Army | E10: Open — Nigeria eligible | F10: See posting | G10: $1.1k/mo | H10: Contract; US clients | I10: Ashby | J10: Oct 2026 | K10: Apply ↗
A11: 5 | B11: Egypt, Argentina, Ethiopia, Nigeria, South Africa | C11: UGC Video Editor | D11: Scale Army | E11: Open — Nigeria eligible | F11: See posting | G11: $1.2k–1.8k/mo | H11: Contract; short-form UGC ads | I11: Ashby | J11: Oct 2026 | K11: Apply ↗
A12: 6 | B12: Philippines, Ghana, India, Jamaica, Kenya, Nigeria, Pakistan | C12: Web Designer | D12: TalentPop | E12: Open — Nigeria eligible | F12: See posting | G12: $9–10/hr | H12: Remote; e-commerce/Shopify web design for TalentPop clients | I12: Ashby | J12: Oct 2026 | K12: Apply ↗
A13: ▸ Nigeria-based remote
A14: 7 | B14: Nigeria-based (remote) | C14: Marketing Designer (Fractional, 2–3 days/week) | D14: Jobgether (partner company) | E14: Open — Nigeria eligible | F14: Mid | G14: Not listed | H14: Contract, part-week | I14: Lever | J14: Oct 2026 | K14: Apply ↗
A15: 8 | B15: Remote, Nigeria (fully remote) | C15: Senior Content Designer | D15: Moniepoint | E15: Open — Nigeria eligible | F15: Senior | G15: Not listed | H15: Degree in English/Comms/Journalism; 3+ yrs UX writing/copywriting; portfolio | I15: Greenhouse | J15: 30 Sep | K15: Apply ↗
A16: 9 | B16: Remote, Nigeria | C16: Senior Illustrator | D16: Moniepoint | E16: Open — Nigeria eligible | F16: Senior (4-5 yrs) | G16: Not listed (pension, HMO, annual bonus) | H16: 4-5 yrs illustration/graphic design; arts/design degree; Illustrator + Photoshop portfolio | I16: Greenhouse | J16: 10 Sep | K16: Apply ↗
A17: 10 | B17: Remote, Nigeria (also India, Poland, Portugal, Spain; or London) | C17: Senior Product Designer (UX) | D17: Moniepoint | E17: Open — Nigeria eligible | F17: Senior | G17: Not listed | H17: 3+ yrs senior product design (UX); advanced Figma incl. tokens/components; fintech/SaaS | I17: Greenhouse | J17: 14 Sep | K17: Apply ↗

Sheet Tech & Operations
A1: Tech & Operations — new remote roles open to Nigeria (10 Oct 2026)
A2: From company career pages (Ashby, Greenhouse, Lever, Workable) and official teaching platforms. Nothing here appears on any earlier ERJ sheet.
A4: # | B4: Who can apply | C4: Role | D4: Company | E4: Status | F4: Level | G4: Pay (as listed) | H4: Key requirements | I4: ATS | J4: Posted | K4: Apply link | L4: Note
A5: ▸ Worldwide / global
A6: 1 | B6: Remote — Global Anywhere | C6: Sr. Insider Risk Analyst | D6: Alpaca | E6: Open — Nigeria eligible | F6: Senior IC | G6: Not listed (+ stock options) | H6: 3+ yrs DLP/data protection; tuning DLP in SaaS/endpoint; alert triage & escalation | I6: Greenhouse | J6: Sep 2026 | K6: Apply ↗
A7: 2 | B7: Remote — "engineers worldwide" | C7: Experienced Software Engineer | D7: Automattic | E7: Open — Nigeria eligible | F7: Mid–Senior | G7: $70,000–$170,000 USD (paid in local currency) | H7: Production PHP & JavaScript; experience at scale; travel 3-4 weeks/yr for meetups | I7: Greenhouse | J7: 21 Sep | K7: Apply ↗
A8: 3 | B8: Remote — fully remote company (no country restriction stated) | C8: Senior Product Manager, Payments | D8: Automattic | E8: Open — Nigeria eligible | F8: Senior IC | G8: $170,000–$240,000 USD | H8: 7+ yrs product incl. senior IC; 4+ yrs payments/fintech; reliability mindset | I8: Greenhouse | J8: 24 Sep | K8: Apply ↗
A9: 4 | B9: Remote — fully remote company (global hiring) | C9: Senior Systems Engineer | D9: Automattic | E9: Open — Nigeria eligible | F9: Senior | G9: $120,000–$180,000+ USD | H9: Large Nginx environments; very large MySQL/MariaDB; PHP apps at scale | I9: Greenhouse | J9: 24 Sep | K9: Apply ↗
A10: 5 | B10: Home based — Worldwide (teams in all time zones) | C10: Software Support Engineer | D10: Canonical | E10: Open — Nigeria eligible | F10: Mid | G10: Not listed | H10: Hands-on Linux/open source; Python, Go, C or C++; CS/STEM background | I10: Greenhouse | J10: Aug–Oct 2026 | K10: Apply ↗ | L10: Up to 10% travel
A11: 6 | B11: "We welcome candidates anywhere in the world" ("Fully remote, worldwide") | C11: Senior Product Manager | D11: Minerva Project | E11: Open — Nigeria eligible | F11: Senior | G11: US$100,000–$125,000/yr | H11: Independent ownership of software product work from problem definition to launch | I11: Breezy HR | J11: 09 Oct 2026 | K11: Apply ↗ | L11: Needs regular working-hour overlap with team
A12: 7 | B12: Remote - Non-US | C12: Threat Intel - AI / LLM Trainer | D12: Remotasks (Scale AI) | E12: Open — Nigeria eligible | F12: Experienced | G12: Not listed (by expertise) | H12: Incident response / threat intel / vuln management; GCIH, GCTI, CISSP, OSCP valued; min 5 hrs/week | I12: Greenhouse | J12: Oct 2026 | K12: Apply ↗
A13: ▸ Region list incl. Nigeria
A14: 8 | B14: 'fully remote - you can be based anywhere in Europe, the Middle East or Africa' | C14: Forward Deployed Engineer, EMEA | D14: Brainbase Labs | E14: Open — Nigeria eligible | F14: Mid-Senior | G14: Not listed | H14: Own 1+ customer accounts post-sale to deployment; hands-on engineering | I14: Ashby | J14: 10 Sep | K14: Apply ↗ | L14: Occasional travel to customer sites
A15: 9 | B15: Remote, work from home - India and Nigeria | C15: Support Engineer - Power Apps & Power Automate | D15: Gigmo Solutions | E15: Open — Nigeria eligible | F15: Mid | G15: Pay-per-ticket (rates shared before first shift) | H15: Canvas & model-driven Power Apps; Power Automate flows; Dataverse | I15: Workable | J15: 18 Sep | K15: Apply ↗ | L15: Flexible 4- or 8-hour shift blocks; no fixed salary
A16: 10 | B16: Fully remote within UTC-1 to UTC+3; listed Lagos, Accra, Nairobi, Kampala, Cape Town, Johannesburg | C16: Senior Backend Engineer - Mobility (12-month FTC) | D16: M-KOPA | E16: Open — Nigeria eligible | F16: Senior | G16: Not listed | H16: C#/.NET; event-driven microservices (Service Bus/Kafka); Azure, Kubernetes | I16: Ashby | J16: 9 Oct | K16: Apply ↗ | L16: 12-month fixed-term contract
A17: 11 | B17: Remote (Europe/Africa time zones): SA, Kenya, Nigeria, Ghana, Rwanda | C17: Staff Software Engineer (Back-End) | D17: OpenFn | E17: Open — Nigeria eligible | F17: Staff (8+ yrs) | G17: Not listed | H17: 8+ yrs backend services; Node.js; designing architectures for reliability at scale | I17: Workable | J17: 10 Sep | K17: Apply ↗
A18: 12 | B18: Egypt, Argentina, Ethiopia, Nigeria, South Africa | C18: Production Manager | D18: Scale Army | E18: Open — Nigeria eligible | F18: Manager | G18: $1.7k–2.2k/mo | H18: Contract; US clients | I18: Ashby | J18: Oct 2026 | K18: Apply ↗
A19: ▸ Nigeria-based remote
A20: 13 | B20: TELECOMMUTE, Nigeria | C20: Senior Software Engineer - AI Code Evaluation | D20: Gramian Consulting Group | E20: Open — Nigeria eligible | F20: Senior (7+ yrs) | G20: Not listed | H20: 7+ yrs; Python/JS/TS/Java/Go; reviewing production code; strong written English | I20: Workable | J20: 1 Oct | K20: Apply ↗ | L20: AI-training/evaluation work
A21: 14 | B21: TELECOMMUTE; Lagos, Nigeria | C21: DevOps Engineer (contract) | D21: Helium Health | E21: Open — Nigeria eligible | F21: Mid (3-5 yrs) | G21: Not listed | H21: 3-5 yrs DevOps; Docker & Kubernetes; Python/Bash; Terraform | I21: Workable | J21: 23 Sep | K21: Apply ↗ | L21: Contract
A22: 15 | B22: Nigeria-based (remote) | C22: Product Engineer (AI-Native) | D22: Jobgether (partner company) | E22: Open — Nigeria eligible | F22: Mid-senior | G22: Not listed | H22: Full-time remote | I22: Lever | J22: Oct 2026 | K22: Apply ↗
A23: 16 | B23: TELECOMMUTE, Nigeria | C23: Remote HubSpot CRM Implementation Specialist | D23: Outsourcing Advantage | E23: Open — Nigeria eligible | F23: Mid | G23: Not listed | H23: Proven HubSpot implementation; CRM customisation & data migration; workflow automation | I23: Workable | J23: 17 Sep | K23: Apply ↗ | L23: Weekends off
A24: 17 | B24: TELECOMMUTE; Lagos, Nigeria - 'Remote work from anywhere in the world' | C24: Product Manager - SME Lending Lead | D24: Renmoney | E24: Open — Nigeria eligible | F24: Senior (4-7 yrs) | G24: Not listed | H24: 4-7 yrs PM; SME/B2B lending background; scaled lending products | I24: Workable | J24: 29 Sep | K24: Apply ↗

Sheet micro1 Referral
A1: micro1 — new roles on your referral link (10 Oct 2026)
A2: Every "Apply ↗" opens that exact role on micro1 with your referral code, so applications are credited to you. Remote AI-training / expert contracts; country eligibility is confirmed during micro1 application.
A4: # | B4: Field | C4: Role | D4: Pay (per hour, as listed) | E4: Openings | F4: Posted | G4: Apply via referral | H4: Note
A5: ▸ AI Training & Admin
A6: 1 | B6: AI Training & Admin | C6: Video Data Annotator | D6: $8–10/hr | E6: 1000 | F6: 9 Oct | G6: Apply ↗ | H6: Opens this role directly on your referral link. Entry level, huge intake
A7: 2 | B7: AI Training & Admin | C7: AI Agent Evaluator | D7: $25–45/hr | E7: 50 | F7: 9 Oct | G7: Apply ↗ | H7: Opens this role directly on your referral link.
A8: 3 | B8: AI Training & Admin | C8: Everyday AI Agent Tester | D8: $25–45/hr | E8: 50 | F8: 9 Oct | G8: Apply ↗ | H8: Opens this role directly on your referral link.
A9: 4 | B9: AI Training & Admin | C9: Human Data Manager | D9: $40–60/hr | E9: 1 | F9: 9 Oct | G9: Apply ↗ | H9: Opens this role directly on your referral link.
A10: 5 | B10: AI Training & Admin | C10: Human Data Manager, New Grad | D10: Not specified | E10: 1 | F10: 9 Oct | G10: Apply ↗ | H10: Opens this role directly on your referral link. Fresh graduates
A11: ▸ Creative & Media
A12: 6 | B12: Creative & Media | C12: Filmmaker | D12: $21–35/hr | E12: 250 | F12: 8 Oct | G12: Apply ↗ | H12: Opens this role directly on your referral link.
A13: 7 | B13: Creative & Media | C13: Sound Designer | D13: $21–35/hr | E13: 250 | F13: 8 Oct | G13: Apply ↗ | H13: Opens this role directly on your referral link.
A14: ▸ Software & Data
A15: 8 | B15: Software & Data | C15: Game Developer | D15: $25–70/hr | E15: 20 | F15: 8 Oct | G15: Apply ↗ | H15: Opens this role directly on your referral link.
A16: ▸ Finance
A17: 9 | B17: Finance | C17: Financial Expert | D17: $30–40/hr | E17: 10 | F17: 9 Oct | G17: Apply ↗ | H17: Opens this role directly on your referral link.
A18: 10 | B18: Finance | C18: Quantitative Rates Researcher | D18: $80–150/hr | E18: 100 | F18: 9 Oct | G18: Apply ↗ | H18: Opens this role directly on your referral link.
A19: 11 | B19: Finance | C19: Rates Trader | D19: $80–100/hr | E19: 20 | F19: 9 Oct | G19: Apply ↗ | H19: Opens this role directly on your referral link.
