Workbook

Sheet Summary
A1: ERJ Remote Job Search Sheet — 23 Oct 2026
A2: Posted 19–23 Oct 2026 (since the 19 Oct sheet), plus your two new career pages · fully remote · open to people living in Nigeria · no link from any earlier ERJ sheet
A4: Tab | B4: Open — Nigeria eligible | C4: Check before applying | D4: Total
A5: Customer Support | B5: =COUNTIF('Customer Support'!$E$5:$E$6,"Open*") -> 1 | C5: =COUNTIF('Customer Support'!$E$5:$E$6,"Check*") -> 0 | D5: =B5+C5 -> 1
A6: VA & Admin | B6: =COUNTIF('VA & Admin'!$E$5:$E$10,"Open*") -> 4 | C6: =COUNTIF('VA & Admin'!$E$5:$E$10,"Check*") -> 0 | D6: =B6+C6 -> 4
A7: HR & Legal | B7: =COUNTIF('HR & Legal'!$E$5:$E$9,"Open*") -> 3 | C7: =COUNTIF('HR & Legal'!$E$5:$E$9,"Check*") -> 0 | D7: =B7+C7 -> 3
A8: Languages & Teaching | B8: =COUNTIF('Languages & Teaching'!$E$5:$E$7,"Open*") -> 2 | C8: =COUNTIF('Languages & Teaching'!$E$5:$E$7,"Check*") -> 0 | D8: =B8+C8 -> 2
A9: Sales & Marketing | B9: =COUNTIF('Sales & Marketing'!$E$5:$E$7,"Open*") -> 2 | C9: =COUNTIF('Sales & Marketing'!$E$5:$E$7,"Check*") -> 0 | D9: =B9+C9 -> 2
A10: Creative & Content | B10: =COUNTIF('Creative & Content'!$E$5:$E$10,"Open*") -> 3 | C10: =COUNTIF('Creative & Content'!$E$5:$E$10,"Check*") -> 0 | D10: =B10+C10 -> 3
A11: Tech & Operations | B11: =COUNTIF('Tech & Operations'!$E$5:$E$11,"Open*") -> 5 | C11: =COUNTIF('Tech & Operations'!$E$5:$E$11,"Check*") -> 0 | D11: =B11+C11 -> 5
A12: 10Alytics (Remote) | B12: =COUNTIF('10Alytics (Remote)'!$E$5:$E$22,"Open*") -> 0 | C12: =COUNTIF('10Alytics (Remote)'!$E$5:$E$22,"Check*") -> 17 | D12: =B12+C12 -> 17
A13: micro1 Referral | B13: =COUNTA('micro1 Referral'!$C$5:$C$16) -> 8 | C13: 0 | D13: =B13+C13 -> 8
A14: Total | B14: =SUM(B5:B13) -> 28 | C14: =SUM(C5:C13) -> 17 | D14: =SUM(D5:D13) -> 45
A16: Notes
A17: • Rule used: the posting names Nigeria, Africa, or worldwide/any country. EMEA-only and plain "Remote" roles were left out, except the 10Alytics tab (see below).
A18: • New sources this round: Openhill Global (3 roles listed "Remote / Nigeria"), 10Alytics (17 roles, all "Remote") and Crossover (2 teaching roles open to Nigeria).
A19: • 10Alytics tab: every role is marked Remote but no countries or posting dates are shown, so those rows are "Check before applying". Openhill roles in London/Singapore and its Full Stack Developer (no country) were left out; so was Crossover VP of Programme Management (hybrid).
A20: • micro1 links open each exact job with your referral code built in. 20four7VA roles all have region preference "Any".
A21: • Also left out: Helium Health roles (on-site), Social Discovery Group roles tied to one country, Gramian US-only and code-licensing posts, micro1 US-licensed attorney, military, macroeconomist and broken-pay roles, and 20four7VA "Offshore or Nearshore"-only roles.

Sheet Customer Support
A1: Customer Support — new remote roles open to Nigeria (23 Oct 2026)
A2: From company career pages (Ashby, Greenhouse, Lever, Workable) and official teaching platforms. Nothing here appears on any earlier ERJ sheet.
A4: # | B4: Who can apply | C4: Role | D4: Company | E4: Status | F4: Level | G4: Pay (as listed) | H4: Key requirements | I4: ATS | J4: Posted | K4: Apply link | L4: Note
A5: ▸ Nigeria-based remote
A6: 1 | B6: Nigeria (remote) | C6: Head of Customer Experience | D6: Jobgether (partner company) | E6: Open — Nigeria eligible | F6: 3+ yrs, team lead | G6: CAD 70k–80k + up to 15% bonus | H6: Customer experience/retention/loyalty; managed a customer-facing team | I6: Lever | J6: 19 Oct | K6: Apply ↗

Sheet VA & Admin
A1: VA & Admin — new remote roles open to Nigeria (23 Oct 2026)
A2: From company career pages (Ashby, Greenhouse, Lever, Workable) and official teaching platforms. Nothing here appears on any earlier ERJ sheet.
A4: # | B4: Who can apply | C4: Role | D4: Company | E4: Status | F4: Level | G4: Pay (as listed) | H4: Key requirements | I4: ATS | J4: Posted | K4: Apply link | L4: Note
A5: ▸ Worldwide / global
A6: 1 | B6: Worldwide; REGION PREFERENCES: Any | C6: Administrative & Student Accounts Virtual Assistant (CPT-11642) | D6: 20four7VA | E6: Open — Nigeria eligible | F6: Entry to mid | G6: Competitive rates, paid weekly (amount not stated) | H6: Business support / admin experience; strong Excel and spreadsheet management; high accuracy with data; professional written English | I6: Breezy | J6: 19 Oct | K6: Apply ↗ | L6: Independent contractor; 10 hrs/wk Mon-Fri, flexible PST hours, may grow
A7: 2 | B7: Worldwide; REGION PREFERENCES: Any | C7: Business Support Virtual Assistant (CPT-11579) | D7: 20four7VA | E7: Open — Nigeria eligible | F7: Entry to mid | G7: Competitive rates, paid weekly (amount not stated) | H7: Spreadsheet and data-entry experience (required); MS Office / Google Workspace; clear written and spoken English; organisation and time management | I7: Breezy | J7: 21 Oct | K7: Apply ↗ | L7: Independent contractor; 20 hrs/wk (VA1) or 40 hrs/wk (VA2-3), Mon-Fri, CST hours TBD
A8: 3 | B8: Worldwide; REGION PREFERENCES: Any | C8: Construction Project Administrative Assistant (CPT-11662) | D8: 20four7VA | E8: Open — Nigeria eligible | F8: Mid-level | G8: Competitive rates, paid weekly (amount not stated) | H8: Admin / project coordination / ops support experience; document management and deadline tracking; Google Workspace and spreadsheets; Bluebeam and ClickUp preferred | I8: Breezy | J8: 22 Oct | K8: Apply ↗ | L8: Independent contractor; 20-30 hrs/wk rising toward 40, Mon-Fri, US hours (EST/MST listed)
A9: ▸ Nigeria-based remote
A10: 4 | B10: Remote / Nigeria | C10: Virtual Assistant (VA) | D10: Openhill Global | E10: Open — Nigeria eligible | F10: See posting | G10: Not listed | H10: Full-time; admin support to the executive and operations team | I10: Company site | J10: Open 23 Oct | K10: Apply ↗

Sheet HR & Legal
A1: HR & Legal — new remote roles open to Nigeria (23 Oct 2026)
A2: From company career pages (Ashby, Greenhouse, Lever, Workable) and official teaching platforms. Nothing here appears on any earlier ERJ sheet.
A4: # | B4: Who can apply | C4: Role | D4: Company | E4: Status | F4: Level | G4: Pay (as listed) | H4: Key requirements | I4: ATS | J4: Posted | K4: Apply link | L4: Note
A5: ▸ Worldwide / global
A6: 1 | B6: Anywhere (100% remote company; core hours for real-time collaboration) | C6: Head of People | D6: VRChat | E6: Open — Nigeria eligible | F6: Senior leadership | G6: Not stated (stock options, unlimited PTO, parental leave) | H6: Led a lean People function at a growing tech company; built people programmes with measurable impact; AI/automation in People workflows; managed fully remote global teams | I6: Lever | J6: 20 Oct | K6: Apply ↗ | L6: Benefits text mentions only US 401K / Canada RRSP; confirm payroll setup for Nigeria
A7: 2 | B7: Anywhere (100% remote company; core hours for real-time collaboration) | C7: Head of Talent | D7: VRChat | E7: Open — Nigeria eligible | F7: Senior / Head | G7: Not stated (stock options, unlimited PTO) | H7: 8+ yrs full-cycle recruiting incl. building a function from scratch; technical sourcing for engineering roles; recruiting systems and onboarding; measurable hiring outcomes | I7: Lever | J7: 20 Oct | K7: Apply ↗ | L7: Benefits text mentions only US 401K / Canada RRSP; confirm payroll setup for Nigeria
A8: ▸ Nigeria-based remote
A9: 3 | B9: Remote / Nigeria | C9: Human Resources Specialist | D9: Openhill Global | E9: Open — Nigeria eligible | F9: See posting | G9: Not listed | H9: Full-time; lead HR initiatives and team culture | I9: Company site | J9: Open 23 Oct | K9: Apply ↗

Sheet Languages & Teaching
A1: Languages & Teaching — new remote roles open to Nigeria (23 Oct 2026)
A2: From company career pages (Ashby, Greenhouse, Lever, Workable) and official teaching platforms. Nothing here appears on any earlier ERJ sheet.
A4: # | B4: Who can apply | C4: Role | D4: Company | E4: Status | F4: Level | G4: Pay (as listed) | H4: Key requirements | I4: ATS | J4: Posted | K4: Apply link | L4: Note
A5: ▸ Worldwide / global
A6: 1 | B6: Remote (listed as open in Nigeria) | C6: AI-Driven Learning Analyst (2 Hour Learning) | D6: Crossover | E6: Open — Nigeria eligible | F6: See posting | G6: $60k/yr ($30/hr) | H6: Analyse learning data with AI tools; full-time; Crossover skills tests | I6: Company site | J6: Open 23 Oct | K6: Apply ↗
A7: 2 | B7: Worldwide, fully remote | C7: Director of Academics (2 Hour Learning) | D7: Crossover | E7: Open — Nigeria eligible | F7: 7+ yrs leadership | G7: $400k/yr ($200/hr) | H7: Education/EdTech leadership; K–12 learning-science expertise; strong AI fluency; full-time 40 hrs/week | I7: Company site | J7: Open 23 Oct | K7: Apply ↗

Sheet Sales & Marketing
A1: Sales & Marketing — new remote roles open to Nigeria (23 Oct 2026)
A2: From company career pages (Ashby, Greenhouse, Lever, Workable) and official teaching platforms. Nothing here appears on any earlier ERJ sheet.
A4: # | B4: Who can apply | C4: Role | D4: Company | E4: Status | F4: Level | G4: Pay (as listed) | H4: Key requirements | I4: ATS | J4: Posted | K4: Apply link | L4: Note
A5: ▸ Worldwide / global
A6: 1 | B6: Worldwide; REGION PREFERENCES: Any | C6: Social Media & Marketing Virtual Assistant (CPT-11672) | D6: 20four7VA | E6: Open — Nigeria eligible | F6: Entry to mid | G6: Competitive rates, paid weekly (amount not stated) | H6: Social media management / marketing support experience; Facebook and Instagram publishing; strong organisation and admin; excellent written English | I6: Breezy | J6: 21 Oct | K6: Apply ↗ | L6: Independent contractor; 10 hrs/wk growing to 20+, Mon-Fri, flexible hours
A7: 2 | B7: Worldwide (also Serbia, Poland, Georgia, Armenia); fully remote | C7: Senior Marketing Analyst | D7: Social Discovery Group | E7: Open — Nigeria eligible | F7: Senior | G7: Not disclosed; 28 vacation + 7 wellness days | H7: A/B testing; strong SQL on large datasets; statistics and backtesting; performance-marketing economics (LTV, CAC, ROAS) and BI tools; English B2+ | I7: Breezy | J7: 19 Oct | K7: Apply ↗ | L7: Python and early-LTV modelling a plus

Sheet Creative & Content
A1: Creative & Content — new remote roles open to Nigeria (23 Oct 2026)
A2: From company career pages (Ashby, Greenhouse, Lever, Workable) and official teaching platforms. Nothing here appears on any earlier ERJ sheet.
A4: # | B4: Who can apply | C4: Role | D4: Company | E4: Status | F4: Level | G4: Pay (as listed) | H4: Key requirements | I4: ATS | J4: Posted | K4: Apply link | L4: Note
A5: ▸ Worldwide / global
A6: 1 | B6: Anywhere (fully remote, no country or time-zone limit stated) | C6: 2D Designer (part-time contract) | D6: VRChat | E6: Open — Nigeria eligible | F6: Mid-level / contract | G6: Hourly; applicants state their own rate | H6: Portfolio of 2D work (marketing graphics, UI/storefront assets); icons, thumbnails and mobile layouts; exporting to platform specs; Photoshop/Illustrator/Figma | I6: Lever | J6: 19 Oct | K6: Apply ↗ | L6: Part-time contract running to end of year; ID, reference and background checks
A7: ▸ Region list incl. Nigeria
A8: 2 | B8: Nigeria (remote); sister postings cover other emerging-market countries | C8: Senior Illustrator & Graphic Artist (Multi-Style Digital Art) | D8: Gramian Consulting Group | E8: Open — Nigeria eligible | F8: Senior / contract | G8: Paid per completed task (each task ~30-40 min) | H8: Professional illustration/design experience; strong multi-style portfolio; advanced Procreate, Illustrator, Photoshop; degree or equivalent; strong written English | I8: Workable | J8: 21 Oct | K8: Apply ↗ | L8: 12-week AI-project contract; selection by portfolio review
A9: ▸ Nigeria-based remote
A10: 3 | B10: Remote / Nigeria | C10: Graphic Designer & Social Media Manager | D10: Openhill Global | E10: Open — Nigeria eligible | F10: See posting | G10: Not listed | H10: Part-time; visual content and social media management | I10: Company site | J10: Open 23 Oct | K10: Apply ↗

Sheet Tech & Operations
A1: Tech & Operations — new remote roles open to Nigeria (23 Oct 2026)
A2: From company career pages (Ashby, Greenhouse, Lever, Workable) and official teaching platforms. Nothing here appears on any earlier ERJ sheet.
A4: # | B4: Who can apply | C4: Role | D4: Company | E4: Status | F4: Level | G4: Pay (as listed) | H4: Key requirements | I4: ATS | J4: Posted | K4: Apply link | L4: Note
A5: ▸ Worldwide / global
A6: 1 | B6: Worldwide; REGION PREFERENCES: Any | C6: Kajabi Website Development & Automation VA (T-CPT-11654) | D6: 20four7VA | E6: Open — Nigeria eligible | F6: Mid-level | G6: Competitive rates, paid weekly (amount not stated) | H6: Hands-on Kajabi development (required); Kajabi checkout, tagging and automations; maintaining existing sites; Zapier and AI-assisted dev preferred | I6: Breezy | J6: 21 Oct | K6: Apply ↗ | L6: Independent contractor; 10 hrs/wk, flexible hours, may increase
A7: 2 | B7: Worldwide (also Armenia, Georgia, Serbia, Poland); fully remote | C7: Junior System Administrator (Monitoring Team) | D7: Social Discovery Group | E7: Open — Nigeria eligible | F7: Junior (2+ yrs) | G7: Not disclosed; 28 vacation + 7 wellness days, health cover or up to $1,000/yr | H7: Linux CLI, SSH/VPN, Bash; Zabbix and Grafana; monitoring basics; Jira/Confluence; English B1+ | I7: Breezy | J7: 21 Oct | K7: Apply ↗ | L7: Shift work: 5/2 x 8h plus 2/2 day and night shifts when covering
A8: 3 | B8: Serbia or worldwide; fully remote | C8: Product Owner (Matchmaking) | D8: Social Discovery Group | E8: Open — Nigeria eligible | F8: Mid to senior | G8: Not disclosed; 28 vacation + 7 wellness days | H8: Customer experience / activation / onboarding product work; discovery products with large listing volumes; search, feed or recommendation relevance; A/B testing and hypotheses | I8: Breezy | J8: 19 Oct | K8: Apply ↗ | L8: Dating/social-discovery products
A9: 4 | B9: Worldwide; fully remote | C9: Senior CV Engineer | D9: Social Discovery Group | E9: Open — Nigeria eligible | F9: Senior (5+ yrs) | G9: Not disclosed; 28 vacation + 7 wellness days | H9: 5+ yrs training diffusion models and modifying architectures; diffusers and transformers libraries; IP-adapters; backend in Python, Go or C# | I9: Breezy | J9: 21 Oct | K9: Apply ↗
A10: ▸ Region list incl. Nigeria
A11: 5 | B11: Nigeria (Abuja), Egypt, Ethiopia, South Africa, Argentina; LATAM / Africa / Eastern Europe | C11: HubSpot RevOps Administrator | D11: Scale Army | E11: Open — Nigeria eligible | F11: Mid-level (2-3+ yrs) | G11: Not stated | H11: 2-3+ yrs HubSpot admin / RevOps; HubSpot for SaaS/subscription; integrations with dialers, call recorders, email; automations, lead routing, lifecycle workflows; reporting dashboards | I11: Ashby | J11: 20 Oct | K11: Apply ↗ | L11: Contract; 9am-5pm PST (US hours); application includes a skills video

Sheet 10Alytics (Remote)
A1: 10Alytics (Remote) — new remote roles open to Nigeria (23 Oct 2026)
A2: From company career pages (Ashby, Greenhouse, Lever, Workable) and official teaching platforms. Nothing here appears on any earlier ERJ sheet.
A4: # | B4: Who can apply | C4: Role | D4: Company | E4: Status | F4: Level | G4: Pay (as listed) | H4: Key requirements | I4: ATS | J4: Posted | K4: Apply link | L4: Note
A5: ▸ Remote — country not stated
A6: 1 | B6: Remote (country not stated on posting) | C6: Brand and Media Associate | D6: 10Alytics (Nigerian-founded) | E6: Check before applying | F6: See posting | G6: Not listed | H6: Apply on the 10Alytics careers page | I6: Company site | J6: Not shown | K6: Apply ↗ | L6: Posting says Remote but doesn't list countries. 10Alytics is Nigerian-founded and hires largely in Nigeria; confirm when applying. No posting date shown.
A7: 2 | B7: Remote (country not stated on posting) | C7: Business Analysis Associate | D7: 10Alytics (Nigerian-founded) | E7: Check before applying | F7: See posting | G7: Not listed | H7: Apply on the 10Alytics careers page | I7: Company site | J7: Not shown | K7: Apply ↗ | L7: Posting says Remote but doesn't list countries. 10Alytics is Nigerian-founded and hires largely in Nigeria; confirm when applying. No posting date shown.
A8: 3 | B8: Remote (country not stated on posting) | C8: Content Creator | D8: 10Alytics (Nigerian-founded) | E8: Check before applying | F8: See posting | G8: Not listed | H8: Apply on the 10Alytics careers page | I8: Company site | J8: Not shown | K8: Apply ↗ | L8: Posting says Remote but doesn't list countries. 10Alytics is Nigerian-founded and hires largely in Nigeria; confirm when applying. No posting date shown.
A9: 4 | B9: Remote (country not stated on posting) | C9: Customer Sales Associate | D9: 10Alytics (Nigerian-founded) | E9: Check before applying | F9: See posting | G9: Not listed | H9: Apply on the 10Alytics careers page | I9: Company site | J9: Not shown | K9: Apply ↗ | L9: Posting says Remote but doesn't list countries. 10Alytics is Nigerian-founded and hires largely in Nigeria; confirm when applying. No posting date shown.
A10: 5 | B10: Remote (country not stated on posting) | C10: Customer Support Associate | D10: 10Alytics (Nigerian-founded) | E10: Check before applying | F10: Mid (2–3 yrs) | G10: Not listed | H10: Apply on the 10Alytics careers page | I10: Company site | J10: Not shown | K10: Apply ↗ | L10: Posting says Remote but doesn't list countries. 10Alytics is Nigerian-founded and hires largely in Nigeria; confirm when applying. No posting date shown.
A11: 6 | B11: Remote (country not stated on posting) | C11: Data Associate | D11: 10Alytics (Nigerian-founded) | E11: Check before applying | F11: See posting | G11: Not listed | H11: Apply on the 10Alytics careers page | I11: Company site | J11: Not shown | K11: Apply ↗ | L11: Posting says Remote but doesn't list countries. 10Alytics is Nigerian-founded and hires largely in Nigeria; confirm when applying. No posting date shown.
A12: 7 | B12: Remote (country not stated on posting) | C12: DevOps Specialist (contract) | D12: 10Alytics (Nigerian-founded) | E12: Check before applying | F12: See posting | G12: Not listed | H12: Apply on the 10Alytics careers page | I12: Company site | J12: Not shown | K12: Apply ↗ | L12: Posting says Remote but doesn't list countries. 10Alytics is Nigerian-founded and hires largely in Nigeria; confirm when applying. No posting date shown.
A13: 8 | B13: Remote (country not stated on posting) | C13: Digital Marketing Specialist (Affiliate Marketing) | D13: 10Alytics (Nigerian-founded) | E13: Check before applying | F13: See posting | G13: Not listed | H13: Apply on the 10Alytics careers page | I13: Company site | J13: Not shown | K13: Apply ↗ | L13: Posting says Remote but doesn't list countries. 10Alytics is Nigerian-founded and hires largely in Nigeria; confirm when applying. No posting date shown.
A14: 9 | B14: Remote (country not stated on posting) | C14: Employability Associate | D14: 10Alytics (Nigerian-founded) | E14: Check before applying | F14: See posting | G14: Not listed | H14: Apply on the 10Alytics careers page | I14: Company site | J14: Not shown | K14: Apply ↗ | L14: Posting says Remote but doesn't list countries. 10Alytics is Nigerian-founded and hires largely in Nigeria; confirm when applying. No posting date shown.
A15: 10 | B15: Remote (country not stated on posting) | C15: Finance Reporting Associate | D15: 10Alytics (Nigerian-founded) | E15: Check before applying | F15: See posting | G15: Not listed | H15: Apply on the 10Alytics careers page | I15: Company site | J15: Not shown | K15: Apply ↗ | L15: Posting says Remote but doesn't list countries. 10Alytics is Nigerian-founded and hires largely in Nigeria; confirm when applying. No posting date shown.
A16: 11 | B16: Remote (country not stated on posting) | C16: Growth Associate | D16: 10Alytics (Nigerian-founded) | E16: Check before applying | F16: See posting | G16: Not listed | H16: Apply on the 10Alytics careers page | I16: Company site | J16: Not shown | K16: Apply ↗ | L16: Posting says Remote but doesn't list countries. 10Alytics is Nigerian-founded and hires largely in Nigeria; confirm when applying. No posting date shown.
A17: 12 | B17: Remote (country not stated on posting) | C17: Human Resource Associate | D17: 10Alytics (Nigerian-founded) | E17: Check before applying | F17: See posting | G17: Not listed | H17: Apply on the 10Alytics careers page | I17: Company site | J17: Not shown | K17: Apply ↗ | L17: Posting says Remote but doesn't list countries. 10Alytics is Nigerian-founded and hires largely in Nigeria; confirm when applying. No posting date shown.
... A22: 17 | B22: Remote (country not stated on posting) | C22: Technical Data Associate | D22: 10Alytics (Nigerian-founded) | E22: Check before applying | F22: See posting | G22: Not listed | H22: Apply on the 10Alytics careers page | I22: Company site | J22: Not shown | K22: Apply ↗ | L22: Posting says Remote but doesn't list countries. 10Alytics is Nigerian-founded and hires largely in Nigeria; confirm when applying. No posting date shown.

Sheet micro1 Referral
A1: micro1 — new roles on your referral link (23 Oct 2026)
A2: Every "Apply ↗" opens that exact micro1 job with your referral code built in, so applications are credited to you. Remote AI-training / expert contracts; country eligibility is confirmed during micro1 application.
A4: # | B4: Field | C4: Role | D4: Pay (per hour, as listed) | E4: Openings | F4: Posted | G4: Apply via referral | H4: Note
A5: ▸ Software & Data
A6: 1 | B6: Software & Data | C6: Data Science & Analytic Methodology SME | D6: $60–100/hr | E6: 3 | F6: 23 Oct | G6: Apply ↗ | H6: LLMs, pipeline integration, data analytics
A7: 2 | B7: Software & Data | C7: Cyber Threat Intelligence SME | D7: $70–110/hr | E7: 3 | F7: 22 Oct | G7: Apply ↗ | H7: Threat-intelligence judgment for AI safety work
A8: 3 | B8: Software & Data | C8: Mathematics Expert (MSc./PhD) | D8: $60–120/hr | E8: 100 | F8: 22 Oct | G8: Apply ↗ | H8: Maths + Python
A9: ▸ Legal
A10: 4 | B10: Legal | C10: Lawyer | D10: $50–80/hr | E10: 10 | F10: 22 Oct | G10: Apply ↗ | H10: Legal research and writing; Bluebook citation and US legal system knowledge
A11: 5 | B11: Legal | C11: Junior Lawyer | D11: $50–80/hr | E11: 10 | F11: 22 Oct | G11: Apply ↗ | H11: Document review against US legal standards; Bluebook
A12: 6 | B12: Legal | C12: Law Student | D12: $50–80/hr | E12: 10 | F12: 22 Oct | G12: Apply ↗ | H12: Legal research/writing; Bluebook, US legal system
A13: ▸ Finance
A14: 7 | B14: Finance | C14: Senior Insurance Claims Expert (Liability, Property, Contents) | D14: $20–60/hr | E14: 20 | F14: 22 Oct | G14: Apply ↗ | H14: Auto liability, property damage assessment
A15: ▸ AI Training & Admin
A16: 8 | B16: AI Training & Admin | C16: Senior Marine Cargo and Draft Surveyor | D16: $20–60/hr | E16: 20 | F16: 22 Oct | G16: Apply ↗ | H16: Cargo condition and draft surveys
